Workbook

Sheet 📋 INDEX
B2: 🛒 Excel Data Analytics — Complete YouTube Tutorial Workbook
B3: E-Commerce Sales Data | Data Cleaning + Validation + Visualization + Dashboard · Telugu YouTube Tutorial
B5: Sheet | C5: Topic | D5: What's Inside
B6: Raw_Data | C6: 📊 Raw Data | D6: 500-row messy e-commerce dataset with 22 columns & all data issues
B7: Data_Cleaning_Steps | C7: 🧹 Cleaning Steps | D7: Step-by-step cleaning guide with formulas, before/after, exercises
B8: Clean_Data | C8: ✅ Clean Data | D8: Fully cleaned and standardized dataset ready for analysis
B9: Data_Validation | C9: ✔️ Data Validation | D9: Validation rules, drop-downs, custom formulas & practice form
B10: Lists | C10: 📋 Reference Lists | D10: Named range reference lists for all dropdown validations
B11: Chart_Data | C11: 📈 Chart Data | D11: Pre-summarized tables for all 5 charts (Region/Monthly/Category/etc.)
B12: Visualization_Guide | C12: 🎨 Visualization Guide | D12: Chart selection guide, step-by-step chart creation & common mistakes
B13: Dashboard | C13: 📊 Dashboard | D13: Interactive KPI dashboard with all business metrics for 2024
B14: Assignment | C14: 🎯 Assignment | D14: 100-mark student assignment with messy dataset to practice on
B16: 💡 How to Use: Start with Raw_Data sheet. Follow the Data_Cleaning_Steps guide. Practice validation in Data_Validation sheet. Build charts from Chart_Data. Replicate the Dashboard. Complete the Assignment!

Sheet Dumy_data
A1: Order_ID | B1: Order_Date | C1: Customer_Name | D1: Customer_ID | E1: Email | F1: Phone | G1: City | H1: State | I1: Region | J1: Product_ID | K1: Product_Name | L1: Category | M1: Sub_Category | N1: Brand | O1: Quantity | P1: Unit_Price | Q1: Discount_% | R1: GST_% | S1: Total_Amount | T1: Payment_Mode | U1: Order_Status | V1: Return_Flag
A2: ORD-1001 | B2: 2024-05-30 | C2: =IF(ISBLANK(Raw_Data!C2),"unknown",PROPER(TRIM(CLEAN(Raw_Data!C2)))) -> Arjun Mehta
A3: ORD-1002 | B3: 29-Jun-2024 | C3: =IF(ISBLANK(Raw_Data!C3),"unknown",PROPER(TRIM(CLEAN(Raw_Data!C3)))) -> Preethi S
A4: ORD-1003 | B4: 2024-06-24 | C4: =IF(ISBLANK(Raw_Data!C4),"unknown",PROPER(TRIM(CLEAN(Raw_Data!C4)))) -> Rekha Pandey
A5: ORD-1004 | B5: 24-Jan-2024 | C5: =IF(ISBLANK(Raw_Data!C5),"unknown",PROPER(TRIM(CLEAN(Raw_Data!C5)))) -> Geetha Rao
A6: ORD-1005 | B6: 09-May-2024 | C6: =IF(ISBLANK(Raw_Data!C6),"unknown",PROPER(TRIM(CLEAN(Raw_Data!C6)))) -> Dinesh K
A7: ORD-1006 | B7: 02/02/2024 | C7: =IF(ISBLANK(Raw_Data!C7),"unknown",PROPER(TRIM(CLEAN(Raw_Data!C7)))) -> Suresh Kumar
A8: ORD-1007 | B8: 28-Feb-2024 | C8: =IF(ISBLANK(Raw_Data!C8),"unknown",PROPER(TRIM(CLEAN(Raw_Data!C8)))) -> Swati Gupta
A9: ORD-1008 | B9: 2024-04-13 | C9: =IF(ISBLANK(Raw_Data!C9),"unknown",PROPER(TRIM(CLEAN(Raw_Data!C9)))) -> Nisha Patel
A10: ORD-1009 | B10: 12-Apr-2024 | C10: =IF(ISBLANK(Raw_Data!C10),"unknown",PROPER(TRIM(CLEAN(Raw_Data!C10)))) -> Kavya Rao
A11: ORD-1010 | B11: 10-May-2024 | C11: =IF(ISBLANK(Raw_Data!C11),"unknown",PROPER(TRIM(CLEAN(Raw_Data!C11)))) -> Rashmi Verma
A12: ORD-1011 | B12: 19-Jan-2024 | C12: =IF(ISBLANK(Raw_Data!C12),"unknown",PROPER(TRIM(CLEAN(Raw_Data!C12)))) -> Geetha Rao
A13: ORD-1012 | B13: 30-Jan-2024 | C13: =IF(ISBLANK(Raw_Data!C13),"unknown",PROPER(TRIM(CLEAN(Raw_Data!C13)))) -> Arun Sharma
... A481: ORD-1480 | B481: Mar-19-2024 | C481: =IF(ISBLANK(Raw_Data!C481),"unknown",PROPER(TRIM(CLEAN(Raw_Data!C481)))) -> Arun Sharma

Sheet Raw_Data
A1: Order_ID | B1: Order_Date | C1: Customer_Name | D1: Customer_ID | E1: Email | F1: Phone | G1: City | H1: State | I1: Region | J1: Product_ID | K1: Product_Name | L1: Category | M1: Sub_Category | N1: Brand | O1: Quantity | P1: Unit_Price | Q1: Discount_% | R1: GST_% | S1: Total_Amount | T1: Payment_Mode | U1: Order_Status | V1: Return_Flag
A2: ORD-1001 | B2: 2024-05-30 | C2: arjun mehta | D2: CUST-001 | E2: arjunmeh@gmail.com | F2: 7815115025 | G2: Hyderabad | H2: Telangana | I2: South | J2: PROD-108 | K2: Nescafe Classic 200g | L2: Grocery | M2: Beverage | N2: Nestlé | O2: 2 | P2: 450 | Q2: 0 | R2: 5 | S2: 945 | T2: CASH | U2: Cancelled | V2: 0
A3: ORD-1002 | B3: 29-Jun-2024 | C3: Preethi S | D3: CUST-002 | E3: @gmail | F3: 9673561638 | G3: Surat | H3: Gujarat | I3: West | J3: PROD-125 | K3: Tanishq Gold Ring | L3: Jewellery | M3: Gold | N3: Tanishq | O3: 10 | P3: 25000 | Q3: 20 | R3: 3 | S3: 206000 | T3: upi | U3: returned | V3: NO
A4: ORD-1003 | B4: 2024-06-24 | C4: rekha pandey | D4: CUST-003 | E4: rekhapan@gmail.com | F4: 769357567 | G4: Bangalore | H4: Karnataka | I4: South | J4: PROD-115 | K4: OnePlus Nord CE 3 | L4: Electronics | M4: Mobile | N4: OnePlus | O4: 5 | P4: 28000 | Q4: 10 | R4: 18 | S4: 148680 | T4: Net Banking | U4: shipped | V4: NO
A5: ORD-1004 | B5: 24-Jan-2024 | C5: Geetha Rao | D5: CUST-004 | E5: geethara@yahoo.com | F5: 7813163240 | G5: Surat | H5: Gujarat | I5: West | J5: PROD-119 | K5: Fastrack Reflex Beat | L5: Fashion | M5: Accessories | N5: Fastrack | O5: 8 | P5: 3500 | Q5: 20 | R5: 18 | S5: 26432 | T5: Debit Card | U5: shipped | V5: 0
A6: ORD-1005 | B6: 09-May-2024 | C6: DINESH K | D6: CUST-005 | E6: dineshk@outlook.com | F6: 6854316681 | G6: Delhi | H6: Delhi | I6: North | J6: PROD-120 | K6: Samsung Galaxy M14 | L6: Electronics | M6: Mobile | N6: Samsung | O6: 1 | P6: 14000 | Q6: 15 | R6: 18 | S6: 14042 | T6: EMI | U6: shipped | V6: no
A7: ORD-1006 | B7: 02/02/2024 | C7: Suresh Kumar | D7: CUST-006 | E7: sureshku@rediffmail.com | F7: 8605301030 | G7: Kochi | H7: Kerala | I7: South | J7: PROD-118 | K7: Voltas 1.5T Desert Cooler | L7: Home | M7: Appliance | N7: Voltas | O7: -3 | P7: 12000 | Q7: 0 | R7: 18 | S7: -42480 | T7: Debit card | U7: Shipped | V7: 1
A8: ORD-1007 | B8: 28-Feb-2024 | C8: swati gupta | D8: CUST-007 | E8: swatigup@outlook.com | F8: 8873237671 | G8: Pune | H8: Maharashtra | I8: West | J8: PROD-125 | K8: Tanishq Gold Ring | L8: Jewellery | M8: Gold | N8: Tanishq | O8: 6 | P8: 25000 | Q8: 136 | R8: 3 | T8: Credit Card | U8: CANCELLED | V8: No
A9: ORD-1008 | B9: 2024-04-13 | C9: nisha patel | D9: CUST-008 | E9: nishapat@gmail.com | F9: 7926780541 | G9: Pune | H9: Maharashtra | I9: West | J9: PROD-124 | K9: Realme Buds Air 3 | L9: Electronics | M9: Audio | N9: Realme | O9: 7 | P9: 2800 | Q9: 25 | R9: 18 | S9: 17346 | T9: Net Banking | U9: Shipped | V9: No
A10: ORD-1009 | B10: 12-Apr-2024 | C10: Kavya Rao | D10: CUST-009 | E10: kavyarao@gmail.com | F10: 9367557574 | G10: Bengaluru | H10: Karnataka | I10: South | J10: PROD-115 | K10: OnePlus Nord CE 3 | L10: Electronics | M10: Mobile | N10: OnePlus | O10: 9 | P10: ₹28,000 | Q10: 5 | R10: 18 | S10: 282492 | T10: Debit card | U10: Dlvrd | V10: NO
A11: ORD-1010 | B11: 10-May-2024 | C11: RASHMI VERMA | D11: CUST-010 | E11: rashmive@gmail.com | F11: 7010193046 | G11: Jaipur | H11: Rajasthan | I11: North | J11: PROD-124 | K11: Realme Buds Air 3 | L11: Electronics | M11: Audio | N11: Realme | O11: 5 | P11: 2800 | Q11: 15 | R11: 18 | S11: 14042 | T11: credit card | U11: Returned | V11: No
A12: ORD-1011 | B12: 19-Jan-2024 | C12: Geetha Rao | D12: CUST-011 | E12: geethara@rediffmail.com | F12: 6915490795 | G12: Bangalore | H12: Karnataka | I12: South | J12: PROD-119 | K12: Fastrack Reflex Beat | L12: Fashion | M12: Accessories | N12: Fastrack | O12: 10 | P12: 3500 | Q12: 15 | R12: 18 | S12: 35105 | T12: EMI | U12: Dlvrd | V12: N
A13: ORD-1012 | B13: 30-Jan-2024 | C13: ARUN SHARMA | D13: CUST-012 | E13: arunshar@yahoo.com | F13: 9082120871 | G13: Surat | H13: Gujarat | I13: West | J13: PROD-112 | K13: Britannia Good Day | L13: Grocery | M13: Snacks | N13: Britannia | O13: 9 | P13: 50 | Q13: 0 | R13: 5 | S13: 472 | T13: Credit Card | U13: Returned | V13: YES
A14: ORD-1013 | B14: 20/01/2024 | C14: Preethi S | D14: CUST-013 | E14: preethis@outlook.com | F14: 6547374338 | G14: Pune | H14: Maharashtra | I14: West | J14: PROD-109 | K14: HP Pavilion Laptop | L14: Electronics | M14: Computer | N14: HP | O14: 7 | P14: 55000 | Q14: 12 | R14: 18 | S14: 399784 | T14: credit card | U14: Delivered | V14: Yes
A15: ORD-1014 | B15: Mar-26-2024 | C15: AMIT SINGH | D15: CUST-014 | E15: amitsing@yahoo.com | F15: 6464267175 | G15: Jaipur | H15: Rajasthan | I15: North | J15: PROD-102 | K15: iPhone 14 Pro | L15: Electronics | M15: Mobile | N15: Apple | O15: 9 | P15: 89000 | Q15: 10 | R15: 18 | S15: 850662 | T15: CASH | U15: Delivered | V15: no
A16: ORD-1015 | B16: 25-Mar-2024 | C16: suresh babu | D16: CUST-015 | E16: sureshba@outlook.com | F16: 7140169349 | G16: Mumbai | H16: Maharashtra | I16: West | J16: PROD-108 | K16: Nescafe Classic 200g | L16: Grocery | M16: Beverage | N16: Nestlé | O16: 4 | P16: 450 | Q16: 5 | R16: 5 | S16: 1796 | T16: CASH | U16: CANCELLED | V16: 1
A17: ORD-1016 | B17: 18-Jun-2024 | C17: AMIT SINGH | D17: CUST-016 | E17: amitsing@outlook.com | F17: 7400944900 | G17: Bangalore | H17: Karnataka | I17: South | J17: PROD-112 | K17: Britannia Good Day | L17: Grocery | M17: Snacks | N17: Britannia | O17: 7 | P17: 50 | Q17: 10 | R17: 5 | S17: 331 | T17: upi | U17: returned | V17: N
A18: ORD-1017 | B18: 21/06/2024 | C18: Geetha Rao | D18: CUST-017 | E18: geethara@yahoo.com | F18: 8851230518 | G18: Jaipur | H18: Rajasthan | I18: North | J18: PROD-107 | K18: Levi's 511 Jeans | L18: Fashion | M18: Clothing | N18: Levi's | O18: 10 | P18: 2500 | Q18: 10 | R18: 5 | S18: 23625 | T18: Debit card | U18: Dlvrd | V18: 0
A19: ORD-1018 | B19: 03/03/2024 | C19: padma lakshmi | D19: CUST-018 | E19: padmalak@gmail.com | F19: 9803044105 | G19: Lucknow | H19: Uttar Pradesh | I19: North | J19: PROD-125 | K19: Tanishq Gold Ring | L19: Jewellery | M19: Gold | N19: Tanishq | O19: 1 | P19: 25000 | Q19: 20 | R19: 3 | S19: 20600 | T19: CASH | U19: Dlvrd | V19: Y
A20: ORD-1019 | B20: 24/04/2024 | C20: DEEPA KRISHNAN | D20: CUST-019 | E20: deepakri@hotmail.com | F20: 9607183629 | G20: Bengaluru | H20: Karnataka | I20: South | J20: PROD-123 | K20: Syska LED Bulb Pack | L20: Home | M20: Lighting | N20: Syska | O20: 8 | P20: 299 | Q20: 15 | R20: 18 | S20: 2399 | T20: credit card | U20: DELIVERED | V20: 1
A21: ORD-1020 | B21: 16/01/2024 | C21: Anita Verma | D21: CUST-020 | E21: anitaver@hotmail.com | F21: 8987248494 | G21: delhi | H21: Delhi | I21: North | J21: PROD-108 | K21: Nescafe Classic 200g | L21: Grocery | M21: Beverage | N21: Nestlé | O21: 6 | P21: 450 | Q21: 8 | R21: 5 | S21: 2608 | T21: credit card | U21: Dlvrd | V21: Y
A22: ORD-1021 | B22: 29/04/2024 | C22: priya sharma | D22: CUST-021 | E22: priyasha@rediffmail.com | G22: bangalor | H22: Karnataka | I22: South | J22: PROD-101 | K22: Samsung TV 43" | L22: Electronics | M22: Television | N22: Samsung | O22: 7 | P22: 35000 | Q22: 25 | R22: 18 | S22: 217734 | T22: Net Banking | U22: DELIVERED | V22: no
A23: ORD-1022 | B23: 18-May-2024 | C23: Geetha Rao | D23: CUST-022 | E23: geethara@outlook.com | F23: 8799264931 | G23: bangalor | H23: Karnataka | I23: South | J23: PROD-101 | K23: Samsung TV 43" | L23: Electronics | M23: Television | N23: Samsung | O23: 5 | P23: 35000 | Q23: 20 | R23: 18 | S23: 165200 | T23: Credit Card | U23: Dlvrd | V23: No
A24: ORD-1023 | B24: 28-May-2024 | C24: AMIT SINGH | D24: CUST-023 | E24: amitsing@rediffmail.com | F24: 7703617827 | G24: Hyderabad | H24: Telangana | I24: South | J24: PROD-107 | K24: Levi's 511 Jeans | L24: Fashion | M24: Clothing | N24: Levi's | O24: 2 | P24: 2500 | Q24: 8 | R24: 5 | S24: 4830 | T24: Debit Card | U24: Pending | V24: Yes
A25: ORD-1024 | B25: Apr-02-2024 | C25: Divya Nair | D25: CUST-024 | E25: divyanai@hotmail.com | F25: 8793693337 | G25: Delhi | H25: Delhi | I25: North | J25: PROD-121 | K25: Amul Butter 500g | L25: Grocery | M25: Dairy | N25: Amul | O25: 2 | P25: 280 | Q25: 15 | R25: 5 | S25: 565 | T25: Debit card | U25: Shipped | V25: Y
A26: ORD-1025 | B26: 24/03/2024 | C26: Anita Verma | D26: CUST-025 | E26: anitaver@outlook.com | F26: 9780945510 | G26: kolkata | H26: West Bengal | I26: East | J26: PROD-118 | K26: Voltas 1.5T Desert Cooler | L26: Home | M26: Appliance | N26: Voltas | O26: 6 | P26: 12000 | Q26: 10 | R26: 18 | S26: 76464 | T26: upi | U26: Delivered | V26: 0
A27: ORD-1026 | B27: 2024-05-01 | C27: DINESH K | D27: CUST-026 | E27: dineshk@rediffmail.com | F27: 7163577186 | G27: Surat | H27: Gujarat | I27: West | J27: PROD-117 | K27: Parle-G Family Pack | L27: Grocery | M27: Snacks | N27: Parle | O27: 4 | P27: 40 | Q27: 5 | R27: 5 | S27: 160 | T27: Net Banking | U27: returned | V27: N
A28: ORD-1027 | B28: 04/01/2024 | C28: SITA DEVI | D28: CUST-027 | E28: sitadevi@gmail.com | F28: 6542366274 | G28: Surat | H28: Gujarat | I28: West | J28: PROD-124 | K28: Realme Buds Air 3 | L28: Electronics | M28: Audio | N28: Realme | O28: 3 | P28: 2800 | Q28: 12 | R28: 18 | S28: 8723 | T28: upi | U28: Returned | V28: YES
A29: ORD-1028 | B29: 04-Mar-2024 | C29: nisha patel | D29: CUST-028 | E29: nishapat@hotmail.com | F29: 6969318858 | G29: Bangalore | H29: Karnataka | I29: South | J29: PROD-119 | K29: Fastrack Reflex Beat | L29: Fashion | M29: Accessories | N29: Fastrack | O29: 5 | P29: 3500 | Q29: 5 | R29: 18 | S29: 19618 | T29: Cash on Delivery | U29: Pending | V29: Yes
A30: ORD-1029 | B30: Jan-01-2024 | C30: deepika rao | D30: CUST-029 | E30: deepikar@rediffmail.com | F30: 754675132 | G30: Visakhapatnam | H30: Andhra Pradesh | I30: South | J30: PROD-115 | K30: OnePlus Nord CE 3 | L30: Electronics | M30: Mobile | N30: OnePlus | O30: 1 | P30: 28000 | Q30: 10 | R30: 18 | S30: 29736 | T30: credit card | U30: Shipped | V30: no
A31: ORD-1030 | B31: Feb-01-2024 | C31: Rahul Gupta | D31: CUST-030 | E31: rahulgup@hotmail.com | F31: 8120834317 | G31: Hydrabad | H31: Telangana | I31: South | J31: PROD-108 | K31: Nescafe Classic 200g | L31: Grocery | M31: Beverage | N31: Nestlé | O31: 4 | P31: 450 | Q31: 8 | R31: 5 | S31: 1739 | T31: Cash on Delivery | U31: Pending | V31: 0
A32: ORD-1031 | B32: May-29-2024 | D32: CUST-031 | E32: user@hotmail.com | F32: 7753841726 | G32: Delhi | H32: Delhi | I32: North | J32: PROD-114 | K32: Philips Mixer Grinder | L32: Home | M32: Kitchen | N32: Philips | O32: 10 | P32: 3200 | Q32: 0 | R32: 18 | S32: 37760 | T32: Debit card | U32: Pending | V32: no
A33: ORD-1032 | B33: 2024-02-18 | C33: Preethi S | D33: CUST-032 | E33: preethis@hotmail.com | F33: 6874275988 | G33: Lucknow | H33: Uttar Pradesh | I33: North | J33: PROD-106 | K33: LG Double Door Refrigerator | L33: Home | M33: Appliance | N33: LG | O33: 9 | P33: 42000 | Q33: 20 | R33: 18 | S33: 643743 | T33: Debit card | U33: DELIVERED | V33: No
A34: ORD-1033 | B34: 2024-05-07 | C34: Anita Verma | D34: CUST-033 | E34: anitaver@outlook.com | F34: 8028168523 | G34: CHENNAI | H34: Tamil Nadu | I34: South | J34: PROD-110 | K34: Banarasi Silk Saree | L34: Fashion | M34: Traditional | N34: Fab India | O34: 10 | P34: ₹3,500 | Q34: 20 | R34: 5 | S34: 29400 | T34: Debit card | U34: Shipped | V34: no
A35: ORD-1034 | B35: Feb-08-2024 | C35: Vijay Patel | D35: CUST-034 | E35: vijaypat@outlook.com | F35: 7620104855 | G35: Hydrabad | H35: Telangana | I35: South | J35: PROD-113 | K35: Titan Raga Watch | L35: Fashion | M35: Accessories | N35: Titan | O35: 2 | P35: 8500 | Q35: 12 | R35: 18 | S35: 17653 | T35: Cash on Delivery | U35: returned | V35: 0
A36: ORD-1035 | B36: 22-Apr-2024 | C36: RASHMI VERMA | D36: CUST-035 | E36: rashmive@hotmail.com | G36: Lucknow | H36: Uttar Pradesh | I36: North | J36: PROD-123 | K36: Syska LED Bulb Pack | L36: Home | M36: Lighting | N36: Syska | O36: 6 | P36: 299 | Q36: 8 | R36: 18 | S36: 1948 | T36: Cash on Delivery | U36: deliverd | V36: Yes
A37: ORD-1036 | B37: 07-Jun-2024 | C37: Suresh Kumar | D37: CUST-036 | E37: sureshku@outlook.com | F37: 7863893256 | G37: Bengaluru | H37: Karnataka | I37: South | J37: PROD-105 | K37: Boat Airdopes 141 | L37: Electronics | M37: Audio | N37: Boat | O37: 7 | P37: 1500 | Q37: 20 | R37: 18 | S37: 9912 | T37: Debit card | U37: shipped | V37: No
A38: ORD-1037 | B38: 07/05/2024 | C38: DEEPA KRISHNAN | D38: CUST-037 | E38: deepakri@outlook.com | F38: 9860782736 | G38: Bangalore | H38: Karnataka | I38: South | J38: PROD-123 | L38: Home | M38: Lighting | N38: Syska | O38: 6 | P38: 299 | Q38: 8 | R38: 18 | S38: 1948 | T38: Cash on Delivery | U38: CANCELLED | V38: NO
A39: ORD-1020 | B39: 16/01/2024 | C39: Anita Verma | D39: CUST-020 | E39: anitaver@hotmail.com | F39: 8987248494 | G39: delhi | H39: Delhi | I39: North | J39: PROD-108 | K39: Nescafe Classic 200g | L39: Grocery | M39: Beverage | N39: Nestlé | O39: 6 | P39: 450 | Q39: 8 | R39: 5 | S39: 2608 | T39: credit card | U39: Dlvrd | V39: Y
A40: ORD-1016 | B40: 18-Jun-2024 | C40: AMIT SINGH | D40: CUST-016 | E40: amitsing@outlook.com | F40: 7400944900 | G40: Bangalore | H40: Karnataka | I40: South | J40: PROD-112 | K40: Britannia Good Day | L40: Grocery | M40: Snacks | N40: Britannia | O40: 7 | P40: 50 | Q40: 10 | R40: 5 | S40: 331 | T40: upi | U40: returned | V40: N
A41: ORD-1038 | B41: Jun-17-2024 | C41: RASHMI VERMA | D41: CUST-038 | E41: rashmive@rediffmail.com | F41: 6210643427 | G41: Jaipur | H41: Rajasthan | I41: North | J41: PROD-106 | K41: LG Double Door Refrigerator | L41: Home | M41: Appliance | N41: LG | O41: 7 | P41: 42000 | Q41: 25 | R41: 18 | S41: 260190 | T41: EMI | U41: Pending | V41: No
A42: ORD-1039 | B42: 2024-05-28 | C42: DINESH K | D42: CUST-039 | E42: dineshk@gmail.com | F42: 7784572192 | G42: MUMBAI | H42: Maharashtra | I42: West | J42: PROD-110 | K42: Banarasi Silk Saree | L42: Fashion | M42: Traditional | N42: Fab India | O42: 4 | P42: 3500 | Q42: 8 | R42: 5 | S42: 13524 | T42: EMI | U42: Dlvrd | V42: No
A43: ORD-1040 | B43: 2024-05-22 | C43: manish tiwari | D43: CUST-040 | E43: manishti@hotmail.com | G43: Pune | H43: Maharashtra | I43: West | J43: PROD-118 | K43: Voltas 1.5T Desert Cooler | L43: Home | M43: Appliance | N43: Voltas | O43: 3 | P43: 12000 | Q43: 15 | R43: 18 | S43: 36108 | T43: Cash | U43: CANCELLED | V43: Y
A44: ORD-1041 | B44: 30/01/2024 | C44: Mohan Lal | D44: CUST-041 | E44: @ | F44: 6417436465 | G44: Bangalore | H44: Karnataka | I44: South | J44: PROD-122 | K44: VIP Trolley Bag | L44: Fashion | M44: Travel | N44: VIP | O44: 6 | Q44: 15 | R44: 18 | S44: 0 | T44: Debit card | U44: Pending | V44: Y
A45: ORD-1042 | B45: 23/04/2024 | C45: Vijay Patel | D45: CUST-042 | E45: vijaypat@gmail.com | F45: 9872755741 | G45: CHENNAI | H45: Tamil Nadu | I45: South | J45: PROD-115 | K45: OnePlus Nord CE 3 | L45: Electronics | M45: Mobile | N45: OnePlus | O45: 10 | P45: 28000 | Q45: 25 | R45: 18 | S45: 247800 | T45: upi | U45: Cancelled | V45: 0
A46: ORD-1043 | B46: 2024-02-29 | C46: Aarav Shah | D46: CUST-043 | E46: aaravsha@rediffmail.com | G46: Mumbai | H46: Maharashtra | I46: West | J46: PROD-107 | K46: Levi's 511 Jeans | L46: Fashion | M46: Clothing | N46: Levi's | O46: 4 | Q46: 10 | R46: 5 | S46: 0 | T46: credit card | U46: Cancelled | V46: NO
A47: ORD-1044 | B47: 25/04/2024 | C47: Suresh Kumar | D47: CUST-044 | E47: sureshku@gmail.com | F47: 8829967158 | G47: Chennai | H47: Tamil Nadu | I47: South | J47: PROD-106 | K47: LG Double Door Refrigerator | L47: Home | M47: Appliance | N47: LG | O47: two | P47: 42000 | Q47: 20 | R47: 18 | S47: 39648 | T47: upi | U47: shipped | V47: Yes
A48: ORD-1045 | B48: 2024-06-01 | C48: deepika rao | D48: CUST-045 | E48: deepikar@rediffmail.com | F48: 6491404673 | G48: Jaipur | H48: Rajasthan | I48: North | J48: PROD-101 | K48: Samsung TV 43" | L48: Electronics | M48: Television | N48: Samsung | O48: 8 | P48: 35000 | Q48: 8 | R48: 18 | S48: 303968 | T48: credit card | U48: deliverd | V48: Y
A49: ORD-1046 | B49: 22-May-2024 | C49: KAVITHA N | D49: CUST-046 | E49: kavithan@rediffmail.com | F49: 7764409657 | G49: Pune | H49: Maharashtra | I49: West | J49: PROD-108 | K49: Nescafe Classic 200g | L49: Grocery | M49: Beverage | N49: Nestlé | O49: 6 | P49: 450 | Q49: 25 | R49: 5 | S49: 2126 | T49: Credit Card | U49: deliverd | V49: no
A50: ORD-1047 | B50: 2024-01-07 | C50: Aarav Shah | D50: CUST-047 | E50: gmail.com | F50: 7459535801 | G50: Bengaluru | H50: Karnataka | I50: South | J50: PROD-124 | K50: Realme Buds Air 3 | L50: Electronics | M50: Audio | N50: Realme | O50: 9 | P50: 2800 | Q50: 15 | R50: 18 | S50: 25276 | T50: CASH | U50: shipped | V50: 1
A51: ORD-1048 | B51: 14/01/2024 | C51: Aarav Shah | D51: CUST-048 | E51: aaravsha@rediffmail.com | G51: Hyderabad | H51: Telangana | I51: South | J51: PROD-105 | K51: Boat Airdopes 141 | L51: Electronics | M51: Audio | N51: Boat | O51: 1 | P51: 1500 | Q51: 8 | R51: 18 | S51: 1628 | T51: Cash on Delivery | U51: returned | V51: Yes
A52: ORD-1049 | B52: 24/02/2024 | C52: Rohit Yadav | D52: CUST-049 | E52: rohityad@outlook.com | F52: 831206151 | G52: Surat | H52: Gujarat | I52: West | J52: PROD-114 | K52: Philips Mixer Grinder | L52: Home | M52: Kitchen | N52: Philips | O52: 2 | P52: 3200 | Q52: 12 | R52: 18 | S52: 6646 | T52: UPI | U52: Cancelled | V52: YES
A53: ORD-1050 | B53: 13-Apr-2024 | C53: manish tiwari | D53: CUST-050 | E53: manishti@yahoo.com | F53: 9573524070 | G53: Chennai | H53: Tamil Nadu | I53: South | J53: PROD-123 | K53: Syska LED Bulb Pack | L53: Home | M53: Lighting | N53: Syska | O53: 7 | Q53: 15 | R53: 18 | S53: 0 | T53: CASH | U53: Pending | V53: Yes
A54: ORD-1051 | B54: 01-Mar-2024 | C54: NEHA SINGH | D54: CUST-051 | E54: nehasing@yahoo.com | F54: 9260534643 | G54: Delhi | H54: Delhi | I54: North | J54: PROD-104 | K54: Prestige Pressure Cooker | L54: Home | M54: Kitchen | N54: Prestige | O54: 5 | P54: 2200 | Q54: 5 | R54: 12 | S54: 11704 | T54: upi | U54: CANCELLED | V54: no
A55: ORD-1052 | B55: 31-Mar-2024 | C55: Meera Nair | D55: CUST-052 | E55: meeranai@hotmail.com | G55: Kolkata | H55: West Bengal | I55: East | J55: PROD-121 | K55: Amul Butter 500g | L55: Grocery | M55: Dairy | N55: Amul | O55: 10 | P55: 280 | Q55: 15 | R55: 5 | S55: 2499 | T55: EMI | U55: Pending | V55: No
A56: ORD-1053 | B56: 14/06/2024 | C56: NEHA SINGH | D56: CUST-053 | E56: @yahoo.com | F56: 8245185702 | G56: Jaipur | H56: Rajasthan | I56: North | J56: PROD-103 | K56: Nike Running Shoes | L56: Fashion | M56: Footwear | N56: Nike | O56: 1 | P56: 4500 | Q56: 25 | R56: 5 | S56: 3544 | T56: upi | U56: Shipped | V56: 1
A57: ORD-1054 | B57: 03-Feb-2024 | C57: padma lakshmi | D57: CUST-054 | E57: padmalak@hotmail.com | F57: 6548870021 | G57: Kolkata | H57: West Bengal | I57: East | J57: PROD-110 | K57: Banarasi Silk Saree | L57: Fashion | M57: Traditional | N57: Fab India | O57: 6 | P57: 3500 | Q57: 8 | R57: 5 | S57: 20286 | T57: upi | U57: Pending | V57: Y
A58: ORD-1055 | B58: 2024-06-18 | C58: deepika rao | D58: CUST-055 | E58: deepikar@rediffmail.com | F58: 6696846464 | G58: Delhi | H58: Delhi | I58: North | J58: PROD-114 | L58: Home | M58: Kitchen | N58: Philips | O58: 6 | P58: 3200 | Q58: 5 | R58: 18 | S58: 21523 | T58: credit card | U58: shipped | V58: No
A59: ORD-1056 | B59: 2024-04-28 | C59: manish tiwari | D59: CUST-056 | E59: manishti@rediffmail.com | F59: 9508521152 | G59: kolkata | H59: West Bengal | I59: East | J59: PROD-106 | K59: LG Double Door Refrigerator | L59: Home | M59: Appliance | N59: LG | O59: 8 | P59: 42000 | Q59: 10 | R59: 18 | S59: 356832 | T59: Cash | U59: deliverd | V59: 0
A60: ORD-1057 | B60: 16-Apr-2024 | C60: Divya Nair | D60: CUST-057 | E60: divyanai@outlook.com | F60: 7610237679 | G60: kolkata | H60: West Bengal | I60: East | J60: PROD-109 | K60: HP Pavilion Laptop | L60: Electronics | M60: Computer | N60: HP | O60: 9 | P60: 55000 | Q60: 8 | R60: 18 | S60: 537372 | T60: Debit card | U60: deliverd | V60: No
A61: ORD-1050 | B61: 13-Apr-2024 | C61: manish tiwari | D61: CUST-050 | E61: manishti@yahoo.com | F61: 9573524070 | G61: Chennai | H61: Tamil Nadu | I61: South | J61: PROD-123 | K61: Syska LED Bulb Pack | L61: Home | M61: Lighting | N61: Syska | O61: 7 | Q61: 15 | R61: 18 | S61: 0 | T61: CASH | U61: Pending | V61: Yes
A62: ORD-1054 | B62: 03-Feb-2024 | C62: padma lakshmi | D62: CUST-054 | E62: padmalak@hotmail.com | F62: 6548870021 | G62: Kolkata | H62: West Bengal | I62: East | J62: PROD-110 | K62: Banarasi Silk Saree | L62: Fashion | M62: Traditional | N62: Fab India | O62: 6 | P62: 3500 | Q62: 8 | R62: 5 | S62: 20286 | T62: upi | U62: Pending | V62: Y
A63: ORD-1058 | B63: May-20-2024 | C63: rekha pandey | D63: CUST-058 | E63: rekhapan@outlook.com | F63: 7024089868 | G63: Hyderabad | H63: Telangana | I63: South | J63: PROD-104 | K63: Prestige Pressure Cooker | L63: Home | M63: Kitchen | N63: Prestige | O63: 5 | P63: 2200 | Q63: 25% | R63: 12 | S63: 9240 | T63: EMI | U63: Cancelled | V63: no
A64: ORD-1059 | B64: 14-May-2024 | C64: MANOJ KUMAR | D64: CUST-059 | E64: manojkum@hotmail.com | G64: kolkata | H64: West Bengal | I64: East | J64: PROD-104 | K64: Prestige Pressure Cooker | L64: Home | M64: Kitchen | N64: Prestige | O64: 10 | P64: 2200 | Q64: 10 | R64: 12 | S64: 22176 | T64: credit card | U64: deliverd | V64: Yes
A65: ORD-1060 | B65: 04-Feb-2024 | C65: suresh babu | D65: CUST-060 | E65: sureshba@hotmail.com | G65: Kochi | H65: Kerala | I65: South | J65: PROD-101 | K65: Samsung TV 43" | L65: Electronics | M65: Television | N65: Samsung | O65: 2 | P65: 35000 | Q65: 15 | R65: 18 | S65: 70210 | T65: Debit card | U65: Dlvrd | V65: no
A66: ORD-1061 | B66: Apr-22-2024 | C66: Divya Nair | D66: CUST-061 | E66: divyanai@yahoo.com | F66: 9969883220 | G66: Mumbai | H66: Maharashtra | I66: West | J66: PROD-102 | K66: iPhone 14 Pro | L66: Electronics | M66: Mobile | N66: Apple | O66: 8 | P66: 89000 | Q66: 0 | R66: 18 | S66: 840160 | T66: upi | U66: DELIVERED | V66: Y
A67: ORD-1062 | B67: 11-Mar-2024 | C67: deepika rao | D67: CUST-062 | E67: deepikar@hotmail.com | F67: 8918046336 | G67: Surat | H67: Gujarat | I67: West | J67: PROD-124 | K67: Realme Buds Air 3 | L67: Electronics | M67: Audio | N67: Realme | O67: 5 | P67: 2800 | Q67: 20 | R67: 18 | S67: 13216 | T67: upi | U67: returned | V67: Y
A68: ORD-1063 | B68: Apr-03-2024 | C68: POOJA IYER | D68: CUST-063 | E68: poojaiye@outlook.com | F68: 9159699467 | G68: Hyderabad | H68: Telangana | I68: South | J68: PROD-120 | K68: Samsung Galaxy M14 | L68: Electronics | M68: Mobile | N68: Samsung | O68: 6 | Q68: 25 | R68: 18 | S68: 0 | T68: Cash on Delivery | U68: Returned | V68: 1
A69: ORD-1064 | B69: 2024-06-19 | C69: manish tiwari | D69: CUST-064 | E69: manishti@rediffmail.com | F69: 9656572173 | G69: MUMBAI | H69: Maharashtra | I69: West | J69: PROD-118 | K69: Voltas 1.5T Desert Cooler | L69: Home | M69: Appliance | N69: Voltas | O69: 10 | P69: 12000 | Q69: 5 | R69: 18 | S69: 134520 | T69: Credit Card | U69: CANCELLED | V69: N
A70: ORD-1065 | B70: 14-Apr-2024 | C70: POOJA IYER | D70: CUST-065 | E70: poojaiye@outlook.com | F70: 8921045865 | G70: Kolkata | H70: West Bengal | I70: East | J70: PROD-117 | K70: Parle-G Family Pack | L70: Grocery | M70: Snacks | N70: Parle | O70: -5 | P70: 40 | Q70: 8 | R70: 5 | S70: -193 | T70: Debit card | U70: shipped | V70: Y
A71: ORD-1066 | B71: 05/03/2024 | C71: deepika rao | D71: CUST-066 | E71: deepikar@rediffmail.com | F71: 8638949369 | G71: Kochi | H71: Kerala | I71: South | J71: PROD-125 | K71: Tanishq Gold Ring | L71: Jewellery | M71: Gold | N71: Tanishq | O71: 9 | P71: 25000 | Q71: 8 | R71: 3 | S71: 213210 | T71: credit card | U71: Pending | V71: Yes
A72: ORD-1067 | B72: 07-Jun-2024 | C72: Mohan Lal | D72: CUST-067 | E72: mohanlal@rediffmail.com | F72: 8074232200 | G72: Delhi | H72: Delhi | I72: North | J72: PROD-106 | K72: LG Double Door Refrigerator | L72: Home | M72: Appliance | N72: LG | O72: 10 | P72: 42000 | Q72: 5 | R72: 18 | S72: 470820 | T72: Net Banking | U72: Cancelled | V72: Y
A73: ORD-1068 | B73: Mar-02-2024 | C73: Vijay Patel | D73: CUST-068 | E73: vijaypat@hotmail.com | F73: 7246451043 | G73: Visakhapatnam | H73: Andhra Pradesh | I73: South | J73: PROD-103 | K73: Nike Running Shoes | L73: Fashion | M73: Footwear | N73: Nike | O73: 6 | P73: 4500 | Q73: 15 | R73: 5 | S73: 24098 | T73: credit card | U73: Shipped | V73: N
A74: ORD-1069 | B74: 13-Jan-2024 | C74: suresh babu | D74: CUST-069 | E74: sureshba@rediffmail.com | F74: 8021155136 | G74: kolkata | H74: West Bengal | I74: East | J74: PROD-106 | K74: LG Double Door Refrigerator | L74: Home | M74: Appliance | N74: LG | O74: 3 | P74: 42000 | Q74: 0 | R74: 18 | S74: 148680 | T74: Cash | U74: Cancelled | V74: N
A75: ORD-1070 | B75: 02-Feb-2024 | C75: Rahul Gupta | D75: CUST-070 | E75: rahulgup@outlook.com | F75: 6619623590 | G75: CHENNAI | H75: Tamil Nadu | I75: south | J75: PROD-114 | K75: Philips Mixer Grinder | L75: Home | M75: Kitchen | N75: Philips | O75: 1 | P75: 3200 | Q75: 5 | R75: 18 | S75: 3587 | T75: Cash on Delivery | U75: CANCELLED | V75: Yes
A76: ORD-1071 | B76: May-09-2024 | C76: Divya Nair | D76: CUST-071 | E76: divyanai@outlook.com | F76: 777832901 | G76: kolkata | H76: West Bengal | I76: East | J76: PROD-117 | K76: Parle-G Family Pack | L76: Grocery | M76: Snacks | N76: Parle | O76: 9 | P76: 40 | Q76: 15 | R76: 5 | S76: 321 | T76: EMI | U76: returned | V76: N
A77: ORD-1072 | B77: 2024-04-22 | C77: arjun mehta | D77: CUST-072 | E77: arjunmeh@hotmail.com | F77: 9328480679 | G77: Bengaluru | H77: Karnataka | I77: South | J77: PROD-124 | K77: Realme Buds Air 3 | L77: Electronics | M77: Audio | N77: Realme | O77: 10 | P77: 2800 | Q77: 20 | R77: 18 | S77: 26432 | T77: Credit Card | U77: Cancelled | V77: No
A78: ORD-1060 | B78: 04-Feb-2024 | C78: suresh babu | D78: CUST-060 | E78: sureshba@hotmail.com | G78: Kochi | H78: Kerala | I78: South | J78: PROD-101 | K78: Samsung TV 43" | L78: Electronics | M78: Television | N78: Samsung | O78: 2 | P78: 35000 | Q78: 15 | R78: 18 | S78: 70210 | T78: Debit card | U78: Dlvrd | V78: no
A79: ORD-1073 | B79: Jun-05-2024 | C79: padma lakshmi | D79: CUST-073 | E79: padmalak@yahoo.com | F79: 7278244804 | G79: MUMBAI | H79: Maharashtra | I79: West | J79: PROD-124 | K79: Realme Buds Air 3 | L79: Electronics | M79: Audio | N79: Realme | O79: 8 | P79: 2800 | Q79: 15 | R79: 18 | S79: 22467 | T79: Net Banking | U79: CANCELLED | V79: YES
A80: ORD-1074 | B80: 2024-01-21 | C80: Rahul Gupta | D80: CUST-074 | E80: rahulgup@outlook.com | F80: 9556025499 | G80: Pune | H80: Maharashtra | I80: West | J80: PROD-116 | K80: Adidas Originals Tee | L80: Fashion | M80: Clothing | N80: Adidas | O80: 5 | P80: 1200 | Q80: 20 | R80: 5 | S80: 5040 | T80: EMI | U80: Delivered | V80: YES
A81: ORD-1075 | B81: Feb-10-2024 | C81: Mohan Lal | D81: CUST-075 | E81: mohanlal@hotmail.com | F81: 7233708056 | G81: Surat | H81: Gujarat | I81: West | J81: PROD-123 | K81: Syska LED Bulb Pack | L81: Home | M81: Lighting | N81: Syska | O81: 1 | P81: 299 | Q81: 20 | R81: 18 | S81: 282 | T81: Debit Card | U81: Delivered | V81: 1
A82: ORD-1076 | B82: 17-Mar-2024 | C82: kiran kumar | D82: CUST-076 | E82: kirankum@outlook.com | F82: 8333457812 | G82: Jaipur | H82: Rajasthan | I82: North | J82: PROD-125 | K82: Tanishq Gold Ring | L82: Jewellery | M82: Gold | N82: Tanishq | O82: 1 | P82: 25000 | Q82: 0 | R82: 3 | S82: 25750 | T82: EMI | U82: Delivered | V82: No
A83: ORD-1077 | B83: 2024-04-19 | C83: deepika rao | D83: CUST-077 | E83: deepikar@gmail.com | F83: 7389858576 | G83: MUMBAI | H83: Maharashtra | I83: West | J83: PROD-105 | K83: Boat Airdopes 141 | L83: Electronics | M83: Audio | N83: Boat | O83: 3 | P83: ₹1,500 | Q83: 15 | R83: 18 | S83: 4514 | T83: Debit Card | U83: returned | V83: Y
A84: ORD-1078 | B84: 04/04/2024 | C84: Vijay Patel | D84: CUST-078 | E84: vijaypat@yahoo.com | F84: 8601628976 | G84: Hyderabad | H84: Telangana | I84: South | J84: PROD-108 | K84: Nescafe Classic 200g | L84: Grocery | M84: Beverage | N84: Nestlé | O84: -3 | P84: 450 | Q84: 12 | R84: 5 | S84: -1247 | T84: EMI | U84: Shipped | V84: YES
A85: ORD-1079 | B85: 08/02/2024 | C85: NEHA SINGH | D85: CUST-079 | E85: nehasing@rediffmail.com | F85: 9079139213 | G85: Bengaluru | H85: Karnataka | I85: South | J85: PROD-116 | K85: Adidas Originals Tee | L85: Fashion | M85: Clothing | N85: Adidas | O85: 10 | P85: 1200 | Q85: 5 | R85: 5 | S85: 11970 | T85: credit card | U85: Cancelled | V85: 1
A86: ORD-1080 | B86: 29-Mar-2024 | C86: Saranya M | D86: CUST-080 | E86: saranyam@gmail.com | F86: 8027530378 | G86: MUMBAI | H86: Maharashtra | I86: West | J86: PROD-117 | K86: Parle-G Family Pack | L86: Grocery | M86: Snacks | N86: Parle | O86: 10 | P86: 40 | Q86: 20% | R86: 5 | S86: 336 | T86: Credit Card | U86: Delivered | V86: Y
A87: ORD-1081 | B87: 31/01/2024 | C87: AMIT SINGH | D87: CUST-081 | E87: amitsing@hotmail.com | F87: 6956447193 | G87: Jaipur | H87: Rajasthan | I87: North | J87: PROD-125 | K87: Tanishq Gold Ring | L87: Jewellery | M87: Gold | N87: Tanishq | O87: 6 | P87: 25000 | Q87: 20 | R87: 3 | S87: 123600 | T87: Debit Card | U87: CANCELLED | V87: N
A88: ORD-1082 | B88: 18-Jan-2024 | C88: Ravi Kumar | D88: CUST-082 | E88: ravikuma@hotmail.com | F88: 6209063208 | G88: Hyderabad | H88: Telangana | I88: South | J88: PROD-115 | K88: OnePlus Nord CE 3 | L88: Electronics | M88: Mobile | N88: OnePlus | O88: 4 | P88: 28000 | Q88: 5 | R88: 18 | S88: 125552 | T88: UPI | U88: Cancelled | V88: NO
A89: ORD-1075 | B89: Feb-10-2024 | C89: Mohan Lal | D89: CUST-075 | E89: mohanlal@hotmail.com | F89: 7233708056 | G89: Surat | H89: Gujarat | I89: West | J89: PROD-123 | K89: Syska LED Bulb Pack | L89: Home | M89: Lighting | N89: Syska | O89: 1 | P89: 299 | Q89: 20 | R89: 18 | S89: 282 | T89: Debit Card | U89: Delivered | V89: 1
A90: ORD-1083 | B90: 2024-03-17 | C90: Vijay Patel | D90: CUST-083 | E90: ravi@ | F90: 8688620050 | G90: Mumbai | H90: Maharashtra | I90: West | J90: PROD-108 | K90: Nescafe Classic 200g | L90: Grocery | M90: Beverage | N90: Nestlé | O90: 5 | P90: 450 | Q90: 15 | R90: 5 | S90: 2008 | T90: credit card | U90: Cancelled | V90: Y
A91: ORD-1084 | B91: Apr-15-2024 | C91: swati gupta | D91: CUST-084 | E91: swatigup@yahoo.com | F91: 7418468740 | G91: CHENNAI | H91: Tamil Nadu | I91: South | J91: PROD-112 | K91: Britannia Good Day | L91: Grocery | M91: Snacks | N91: Britannia | O91: 7 | P91: 50 | Q91: 10 | R91: 5 | S91: 331 | T91: Debit card | U91: Delivered | V91: 1
A92: ORD-1085 | B92: Jan-31-2024 | C92: Rohit Yadav | D92: CUST-085 | E92: rohityad@rediffmail.com | F92: 7027918636 | G92: Hydrabad | H92: Telangana | I92: South | J92: PROD-103 | K92: Nike Running Shoes | L92: Fashion | M92: Footwear | N92: Nike | O92: 10 | P92: 4500 | Q92: 10 | R92: 5 | S92: 42525 | T92: UPI | U92: Cancelled | V92: NO
A93: ORD-1086 | B93: 2024-01-05 | C93: KAVITHA N | D93: CUST-086 | E93: kavithan@rediffmail.com | F93: 6654602021 | G93: Lucknow | H93: Uttar Pradesh | I93: North | J93: PROD-113 | K93: Titan Raga Watch | L93: Fashion | M93: Accessories | N93: Titan | O93: 8 | P93: 8500 | Q93: 15 | R93: 18 | S93: 68204 | T93: Cash on Delivery | U93: Cancelled | V93: no
A94: ORD-1087 | B94: 18-May-2024 | C94: Divya Nair | D94: CUST-087 | E94: divyanai@gmail.com | F94: 9282810353 | G94: Lucknow | H94: Uttar Pradesh | I94: North | J94: PROD-119 | K94: Fastrack Reflex Beat | L94: Fashion | M94: Accessories | N94: Fastrack | O94: 5 | P94: 3500 | Q94: 25 | R94: 18 | S94: 15488 | T94: credit card | U94: Dlvrd | V94: no
A95: ORD-1088 | B95: 14-Mar-2024 | D95: CUST-088 | E95: user@hotmail.com | F95: 6459632043 | G95: Bengaluru | H95: Karnataka | I95: South | J95: PROD-121 | K95: Amul Butter 500g | L95: Grocery | M95: Dairy | N95: Amul | O95: 6 | P95: 280 | Q95: 135 | R95: 5 | T95: credit card | U95: Pending | V95: 1
A96: ORD-1089 | B96: Apr-13-2024 | C96: DEEPA KRISHNAN | D96: CUST-089 | E96: deepakri@hotmail.com | F96: 692010856 | G96: delhi | H96: Delhi | I96: North | J96: PROD-107 | K96: Levi's 511 Jeans | L96: Fashion | M96: Clothing | N96: Levi's | O96: 2 | P96: 2500 | Q96: 10 | R96: 5 | S96: 4725 | T96: Net Banking | U96: Delivered | V96: Yes
A97: ORD-1090 | B97: 2024-02-15 | C97: Rohit Yadav | D97: CUST-090 | E97: @gmail | F97: 9061072141 | G97: MUMBAI | H97: Maharashtra | I97: West | J97: PROD-121 | K97: Amul Butter 500g | L97: Grocery | M97: Dairy | N97: Amul | O97: 9 | P97: 280 | Q97: 25 | R97: 5 | S97: 1984 | T97: EMI | U97: shipped | V97: No
A98: ORD-1091 | B98: Mar-28-2024 | C98: Geetha Rao | D98: CUST-091 | E98: geethara@outlook.com | G98: Delhi | H98: Delhi | I98: North | J98: PROD-119 | K98: Fastrack Reflex Beat | L98: Fashion | M98: Accessories | N98: Fastrack | O98: 6 | P98: 3500 | Q98: 5 | R98: 18 | S98: 23541 | T98: CASH | U98: Cancelled | V98: Yes
A99: ORD-1077 | B99: 2024-04-19 | C99: deepika rao | D99: CUST-077 | E99: deepikar@gmail.com | F99: 7389858576 | G99: MUMBAI | H99: Maharashtra | I99: West | J99: PROD-105 | K99: Boat Airdopes 141 | L99: Electronics | M99: Audio | N99: Boat | O99: 3 | P99: ₹1,500 | Q99: 15 | R99: 18 | S99: 4514 | T99: Debit Card | U99: returned | V99: Y
A100: ORD-1082 | B100: 18-Jan-2024 | C100: Ravi Kumar | D100: CUST-082 | E100: ravikuma@hotmail.com | F100: 6209063208 | G100: Hyderabad | H100: Telangana | I100: South | J100: PROD-115 | K100: OnePlus Nord CE 3 | L100: Electronics | M100: Mobile | N100: OnePlus | O100: 4 | P100: 28000 | Q100: 5 | R100: 18 | S100: 125552 | T100: UPI | U100: Cancelled | V100: NO
...

Sheet Data_Cleaning_Steps
A1: 🧹 DATA CLEANING STEPS — Step-by-Step Guide with Formulas, Before/After Examples & Mini Exercises
A2: STEP 01 — REMOVE DUPLICATES
A3: Telugu: Data lo same Order_ID rendu sarlu vastundi. Idi totals ni wrongly double chestundi. COUNTIF formula use chesi flag cheyyi, tarvata Data → Remove Duplicates use cheyyandi.
A4: Step | B4: Action | C4: Formula / Method | D4: Expected Result
A5: 1 | B5: Add helper column 'Dup_Flag' in column W | C5: =IF(COUNTIF($A2:$A$3,A3)>1,"DUPLICATE","UNIQUE") -> UNIQUE | D5: Shows DUPLICATE for repeated Order_IDs
A6: 2 | B6: Filter column W for 'DUPLICATE' | C6: Data → Filter → Filter by 'DUPLICATE' | D6: All duplicate rows visible
A7: 3 | B7: Review and delete duplicates | C7: Select rows → Right click → Delete Row | D7: ~20 duplicate rows removed
A8: 4 | B8: Alternative: Use Excel built-in | C8: Data tab → Remove Duplicates → Select 'Order_ID' → OK | D8: Excel removes dupes automatically
A9: 5 | B9: Verify count after removal | C9: {=COUNTA(A3:A502)-SUMPRODUCT((COUNTIF(A3:A502,A3:A502)>1)/COUNTIF(A3:A502,A3:A502))} -> #DIV/0! | D9: Should equal 0 duplicates remaining
A10: ✏️ MINI EXERCISE: Open Raw_Data sheet. Add column W named 'Dup_Flag'. Write the formula. Count how many duplicates exist. Record the number.
A12: STEP 02 — TRIM & CLEAN — Remove Extra Spaces & Hidden Characters
A13: Function | B13: Syntax | C13: Before | D13: After | E13: Apply To
A14: TRIM | B14: =TRIM(text) -> #NAME? | C14: Sneha Reddy | D14: Sneha Reddy | E14: Customer_Name, City, Product_Name
A15: CLEAN | B15: =CLEAN(text) -> #NAME? | C15: Ravi Kumar | D15: Ravi Kumar | E15: Data imported from other systems
A16: TRIM+CLEAN | B16: =TRIM(CLEAN(C3)) | C16: AMIT SINGH | D16: AMIT SINGH | E16: Use both together always
A17: With PROPER | B17: =PROPER(TRIM(CLEAN(C3))) | C17: amit singh | D17: Amit Singh | E17: Best practice for names
A18: ✏️ MINI EXERCISE: Create Clean_Data sheet. Copy headers. In C3 write =PROPER(TRIM(CLEAN(Raw_Data!C3))). Copy down all 500 rows. Count how many changed.
A20: STEP 03 — HANDLE MISSING VALUES (BLANKS)
A21: Column | B21: Detection Formula | C21: Fill Strategy | D21: Formula
A22: Customer_Name | B22: =COUNTBLANK(C3:C502) -> 451 | C22: Fill with 'Unknown' | D22: =IF(ISBLANK(Raw_Data!C2),"Unknown",PROPER(TRIM(Raw_Data!C2))) -> Arjun Mehta
A23: Customer_ID | B23: =COUNTBLANK(D3:D502) -> 452 | C23: Flag as 'MISSING' | D23: =IF(ISBLANK(Raw_Data!D2),"MISSING",Raw_Data!D2) -> CUST-001
A24: Phone | B24: =COUNTBLANK(G3:G502) -> 500 | C24: Fill 'Not Provided' | D24: =IF(OR(ISBLANK(Raw_Data!G2),Raw_Data!G2=""),"Not Provided",Raw_Data!G2) -> Hyderabad
A25: Unit_Price | B25: =COUNTBLANK(Q3:Q502) -> 500 | C25: Fill 0 & Flag | D25: =IF(ISBLANK(Raw_Data!Q2),0,Raw_Data!Q2) -> 0
A26: Product_Name | B26: =COUNTBLANK(L3:L502) -> 500 | C26: Flag 'Check Required' | D26: =IF(ISBLANK(Raw_Data!L2),"Check Required",PROPER(TRIM(Raw_Data!L2))) -> Grocery
A27: ✏️ MINI EXERCISE: Use COUNTBLANK() to create a data quality summary — count blanks in each of the 22 columns and list them in a table.
A29: STEP 04 — FIX DATE FORMATS — Standardize to DD-MMM-YYYY
A30: Issue | B30: Example Input | C30: Problem | D30: Fix Formula | E30: Clean Output
A31: Mixed separators | B31: 15/01/2024 | C31: DD/MM or MM/DD ambiguous | D31: =DATEVALUE(TEXT(B3,"DD-MM-YYYY")) -> #VALUE! | E31: 15-Jan-2024
A32: ISO format | B32: 2024-01-15 | C32: Text not recognized | D32: =DATE(LEFT(B3,4),MID(B3,6,2),RIGHT(B3,2)) -> #VALUE! | E32: 15-Jan-2024
A33: US format | B33: Jan-17-2024 | C33: Month-Day-Year order | D33: =DATEVALUE(B3) -> #VALUE! | E33: 17-Jan-2024
A34: Extract Day | B34: 15-Jan-2024 | C34: Need Day number | D34: =DAY(B3) -> 0 | E34: 15
A35: Extract Month Name | B35: 15-Jan-2024 | C35: Need Month name | D35: =TEXT(B3,"MMMM") -> January | E35: January
A36: Extract Year | B36: 15-Jan-2024 | C36: Need Year | D36: =YEAR(B3) -> 1900 | E36: 2024
A37: Day of Week | B37: 15-Jan-2024 | C37: Need weekday | D37: =TEXT(B3,"DDDD") -> Saturday | E37: Monday
A38: ✏️ MINI EXERCISE: Add 3 new columns to Clean_Data: Order_Day, Order_Month, Order_Year using DAY(), MONTH(), YEAR() functions on the cleaned date column.
A40: STEP 05 — STANDARDIZE CATEGORIES & TEXT FIELDS
A41: Column | B41: Issue | C41: Before | D41: Formula | E41: After
A42: Category | B42: Wrong casing/typo | C42: Electronicss | D42: =IF(LOWER(TRIM(L3))="electronics","Electronics",IF(LOWER(TRIM(L3))="fashion","Fashion",IF(LOWER(TRIM(L3))="grocery","Grocery",IF(LOWER(TRIM(L3))="home","Home","Check Required")))) -> Check Required | E42: Electronics
A43: Order_Status | B43: Inconsistent | C43: deliverd | D43: =IF(LOWER(TRIM(U3))="delivered","Delivered",IF(LOWER(TRIM(U3))="shipped","Shipped",IF(LOWER(TRIM(U3))="returned","Returned",IF(LOWER(TRIM(U3))="cancelled","Cancelled","Pending")))) -> Pending | E43: Delivered
A44: Region | B44: Typos/wrong values | C44: Soth | D44: =IFERROR(_xludf.SWITCH(LOWER(TRIM(I3)),"north","North","south","South","east","East","west","West"),"Check Required") -> Check Required | E44: South
A45: Return_Flag | B45: Inconsistent | C45: NO / N / 0 | D45: =IF(OR(LOWER(TRIM(V3))="yes",TRIM(V3)="1",TRIM(V3)="y"),"Yes","No") -> No | E45: No
A46: Payment_Mode | B46: Mixed case | C46: upi | D46: =PROPER(IF(LOWER(TRIM(T3))="upi","UPI",TRIM(T3))) | E46: UPI
A47: ✏️ MINI EXERCISE: Write a COUNTIF formula to count how many rows have 'Check Required' in the cleaned Category column. What % of total is this?
A49: STEP 06 — FIX INVALID NUMBERS (Quantity, Discount, Price)
A50: Column | B50: Issue | C50: Detection Formula | D50: Fix Formula | E50: Validation Rule
A51: Quantity | B51: Negative values & text | C51: =IF(OR(NOT(ISNUMBER(O3)),O3<1,O3>100),"INVALID","OK") -> INVALID | D51: =IF(OR(NOT(ISNUMBER(Raw_Data!O2)),Raw_Data!O2<1),1,Raw_Data!O2) -> 2 | E51: Must be 1–100 whole number
A52: Discount_% | B52: Values > 80 or negative | C52: =IF(OR(NOT(ISNUMBER(R3)),R3<0,R3>80),"INVALID","OK") -> INVALID | D52: =IF(OR(NOT(ISNUMBER(Raw_Data!R2)),Raw_Data!R2>80),0,IF(Raw_Data!R2<0,0,Raw_Data!R2)) -> 5 | E52: Must be 0–80 decimal
A53: Unit_Price | B53: Blank or text format | C53: =IF(OR(ISBLANK(Q3),NOT(ISNUMBER(Q3))),"MISSING","OK") -> MISSING | D53: =IFERROR(VALUE(SUBSTITUTE(SUBSTITUTE(Raw_Data!Q2,"₹",""),",","")),0) -> 0 | E53: Must be positive number
A54: Total_Amount | B54: Wrong calculation | C54: =ABS(S3-(O3*Q3*(1-R3/100)*(1+S3/100)))>1 -> FALSE | D54: =ROUND(O3*Q3*(1-R3/100)*(1+S3/100),0) -> 0 | E54: Recalculate from parts
A55: ✏️ MINI EXERCISE: Count negative Quantity rows: =COUNTIF(O3:O502,"<0"). Count Discount > 80: =COUNTIF(R3:R502,">80"). These are your 'critical' errors.
A57: 📋 DATA CLEANING SUMMARY — Issues Found & Fixed
A58: # | B58: Issue Type | C58: Column(s) | D58: Count (Approx) | E58: Formula Used | F58: Status
A59: 1 | B59: Duplicate Records | C59: Order_ID | D59: ~20 | E59: =COUNTIF($A2:$A$3,A3)>1 -> FALSE | F59: Fix with Remove Duplicates
A60: 2 | B60: Extra Spaces | C60: Customer_Name, City | D60: ~45 | E60: =TRIM(CLEAN(C3)) | F60: Fixed with TRIM+CLEAN
A61: 3 | B61: Wrong Casing | C61: Customer_Name, City | D61: ~80 | E61: =PROPER(TRIM(C3)) | F61: Fixed with PROPER
A62: 4 | B62: Blank Customer Names | C62: Customer_Name | D62: ~15 | E62: =IF(ISBLANK(C3),"Unknown",C3) -> Unknown | F62: Filled with 'Unknown'
A63: 5 | B63: Blank Phone Numbers | C63: Phone | D63: ~25 | E63: =IF(ISBLANK(G3),"Not Provided",G3) -> Not Provided | F63: Flagged as 'Not Provided'
A64: 6 | B64: Invalid Date Formats | C64: Order_Date | D64: ~30 | E64: =TEXT(B3,"DD-MMM-YYYY") -> 00-Jan-1900 | F64: Standardized to DD-MMM-YYYY
A65: 7 | B65: Invalid Categories | C65: Category | D65: ~25 | E65: SWITCH/IF on LOWER(TRIM) | F65: Standardized categories
A66: 8 | B66: Negative Quantities | C66: Quantity | D66: ~15 | E66: =IF(O3<1,1,O3) -> 1 | F66: Flagged & corrected
A67: 9 | B67: Discount > 80% | C67: Discount_% | D67: ~10 | E67: =IF(R3>80,0,R3) -> 0 | F67: Set to 0 for review
A68: 10 | B68: Invalid Region Values | C68: Region | D68: ~30 | E68: SWITCH on LOWER(TRIM) | F68: Standardized to 4 valid values
A69: 11 | B69: Blank Product Names | C69: Product_Name | D69: ~15 | E69: =IF(ISBLANK(L3),"Check Required",L3) -> Check Required | F69: Flagged for review
A70: 12 | B70: Text in Number columns | C70: Quantity, Price | D70: ~12 | F70: Converted to numbers

Sheet Clean_Data
A1: ✅ CLEAN DATA — Processed & Standardized Dataset | Ready for Analysis
A2: Order_ID | B2: Order_Date | C2: Customer_Name | D2: Customer_ID | E2: Email | F2: Phone | G2: City | H2: State | I2: Region | J2: Product_ID | K2: Product_Name | L2: Category | M2: Sub_Category | N2: Brand | O2: Quantity | P2: Unit_Price | Q2: Discount_% | R2: GST_% | S2: Total_Amount | T2: Payment_Mode | U2: Order_Status | V2: Return_Flag
A3: ORD-1001 | B3: 2024-04-07 | C3: Arjun Mehta | D3: CUST-001 | E3: arjunmeh@gmail.com | F3: 7815115025 | G3: Hyderabad | H3: Telangana | I3: South | J3: PROD-108 | K3: Nescafe Classic 200G | L3: Grocery | M3: Beverage | N3: Nestlé | O3: 2 | P3: 450 | Q3: 0 | R3: 5 | S3: 945 | T3: Cash | U3: Cancelled | V3: No
A4: ORD-1002 | B4: 2024-04-02 | C4: Preethi S | D4: CUST-002 | E4: preethi@gmail.com | F4: 9673561638 | G4: Surat | H4: Gujarat | I4: West | J4: PROD-125 | K4: Tanishq Gold Ring | L4: Jewellery | M4: Gold | N4: Tanishq | O4: 10 | P4: 25000 | Q4: 20 | R4: 3 | S4: 206000 | T4: UPI | U4: Returned | V4: No
A5: ORD-1003 | B5: 2024-03-02 | C5: Rekha Pandey | D5: CUST-003 | E5: rekhapan@gmail.com | F5: Not Provided | G5: Bangalore | H5: Karnataka | I5: South | J5: PROD-115 | K5: Oneplus Nord Ce 3 | L5: Electronics | M5: Mobile | N5: Oneplus | O5: 5 | P5: 28000 | Q5: 10 | R5: 18 | S5: 148680 | T5: Net Banking | U5: Shipped | V5: No
A6: ORD-1004 | B6: 2024-04-26 | C6: Geetha Rao | D6: CUST-004 | E6: geethara@yahoo.com | F6: 7813163240 | G6: Surat | H6: Gujarat | I6: West | J6: PROD-119 | K6: Fastrack Reflex Beat | L6: Fashion | M6: Accessories | N6: Fastrack | O6: 8 | P6: 3500 | Q6: 20 | R6: 18 | S6: 26432 | T6: Debit Card | U6: Shipped | V6: No
A7: ORD-1005 | B7: 2024-06-23 | C7: Dinesh K | D7: CUST-005 | E7: dineshk@outlook.com | F7: 6854316681 | G7: Delhi | H7: Delhi | I7: North | J7: PROD-120 | K7: Samsung Galaxy M14 | L7: Electronics | M7: Mobile | N7: Samsung | O7: 1 | P7: 14000 | Q7: 15 | R7: 18 | S7: 14042 | T7: EMI | U7: Shipped | V7: No
A8: ORD-1006 | B8: 2024-05-04 | C8: Suresh Kumar | D8: CUST-006 | E8: sureshku@rediffmail.com | F8: 8605301030 | G8: Kochi | H8: Kerala | I8: South | J8: PROD-118 | K8: Voltas 1.5T Desert Cooler | L8: Home | M8: Appliance | N8: Voltas | O8: 1 | P8: 12000 | Q8: 0 | R8: 18 | S8: 14160 | T8: Debit Card | U8: Shipped | V8: Yes
A9: ORD-1007 | B9: 2024-05-03 | C9: Swati Gupta | D9: CUST-007 | E9: swatigup@outlook.com | F9: 8873237671 | G9: Pune | H9: Maharashtra | I9: West | J9: PROD-125 | K9: Tanishq Gold Ring | L9: Jewellery | M9: Gold | N9: Tanishq | O9: 6 | P9: 25000 | Q9: 80 | R9: 3 | S9: 30900 | T9: Credit Card | U9: Cancelled | V9: No
A10: ORD-1008 | B10: 2024-06-21 | C10: Nisha Patel | D10: CUST-008 | E10: nishapat@gmail.com | F10: 7926780541 | G10: Pune | H10: Maharashtra | I10: West | J10: PROD-124 | K10: Realme Buds Air 3 | L10: Electronics | M10: Audio | N10: Realme | O10: 7 | P10: 2800 | Q10: 25 | R10: 18 | S10: 17346 | T10: Net Banking | U10: Shipped | V10: No
A11: ORD-1009 | B11: 2024-03-17 | C11: Kavya Rao | D11: CUST-009 | E11: kavyarao@gmail.com | F11: 9367557574 | G11: Bengaluru | H11: Karnataka | I11: South | J11: PROD-115 | K11: Oneplus Nord Ce 3 | L11: Electronics | M11: Mobile | N11: Oneplus | O11: 9 | P11: 28000 | Q11: 5 | R11: 18 | S11: 282492 | T11: Debit Card | U11: Delivered | V11: No
A12: ORD-1010 | B12: 2024-05-19 | C12: Rashmi Verma | D12: CUST-010 | E12: rashmive@gmail.com | F12: 7010193046 | G12: Jaipur | H12: Rajasthan | I12: North | J12: PROD-124 | K12: Realme Buds Air 3 | L12: Electronics | M12: Audio | N12: Realme | O12: 5 | P12: 2800 | Q12: 15 | R12: 18 | S12: 14042 | T12: Credit Card | U12: Returned | V12: No
A13: ORD-1011 | B13: 2024-06-18 | C13: Geetha Rao | D13: CUST-011 | E13: geethara@rediffmail.com | F13: 6915490795 | G13: Bangalore | H13: Karnataka | I13: South | J13: PROD-119 | K13: Fastrack Reflex Beat | L13: Fashion | M13: Accessories | N13: Fastrack | O13: 10 | P13: 3500 | Q13: 15 | R13: 18 | S13: 35105 | T13: EMI | U13: Delivered | V13: No
A14: ORD-1012 | B14: 2024-05-13 | C14: Arun Sharma | D14: CUST-012 | E14: arunshar@yahoo.com | F14: 9082120871 | G14: Surat | H14: Gujarat | I14: West | J14: PROD-112 | K14: Britannia Good Day | L14: Grocery | M14: Snacks | N14: Britannia | O14: 9 | P14: 50 | Q14: 0 | R14: 5 | S14: 472 | T14: Credit Card | U14: Returned | V14: Yes
... A482: ORD-1480 | B482: 2024-05-16 | C482: Sneha Reddy | D482: CUST-480 | E482: snehared@outlook.com | F482: Not Provided | G482: Kolkata | H482: West Bengal | I482: East | J482: PROD-124 | K482: Realme Buds Air 3 | L482: Electronics | M482: Audio | N482: Realme | O482: 3 | P482: 2800 | Q482: 8 | R482: 18 | S482: 9119 | T482: UPI | U482: Delivered | V482: No
A484: 💡 ✅ Clean Data: 480 rows after removing ~20 duplicates & fixing all data quality issues | Ready for Pivot Tables & Dashboard

Sheet Data_Validation
A1: ✅ DATA VALIDATION — Rules, Drop-downs & Custom Formulas
A2: 📌 Telugu: Data entry time lo wrong values enter avvakaundaniki Data Validation use chestham. Idi prevent chestundi errors before they happen!
A4: REFERENCE LISTS (Named Ranges for Validations)
A5: Valid Regions | B5: Valid Categories | C5: Valid Payment Modes | D5: Valid Order Status | E5: Valid Return Flag | F5: Valid States
A6: North | B6: Electronics | C6: UPI | D6: Delivered | E6: Yes | F6: Telangana
A7: South | B7: Fashion | C7: Credit Card | D7: Shipped | E7: No | F7: Maharashtra
A8: East | B8: Grocery | C8: Debit Card | D8: Returned | F8: Delhi
A9: West | B9: Home | C9: Cash | D9: Cancelled | F9: Karnataka
B10: Jewellery | C10: EMI | D10: Pending | F10: Tamil Nadu
C11: Net Banking | F11: Gujarat
F12: Rajasthan
F13: West Bengal
F14: Uttar Pradesh
F15: Kerala
F16: Andhra Pradesh
A18: VALIDATION RULES GUIDE — How to Apply Each Rule
A19: # | B19: Column | C19: Validation Type | D19: Settings | E19: Error Message | F19: Step-by-Step
A20: 1 | B20: Region (I) | C20: List | D20: Source: North,South,East,West | E20: Invalid! Select: North/South/East/West | F20: Data → Validation → Allow: List → Source: North,South,East,West
A21: 2 | B21: Category (L) | C21: List | D21: Source: =CategoryList (named range) | E21: Invalid Category! Use the dropdown. | F21: Create named range first, then Data → Validation → List → =CategoryList
A22: 3 | B22: Quantity (O) | C22: Whole Number | D22: Min: 1 | Max: 100 | E22: Quantity must be between 1 and 100 | F22: Data → Validation → Whole Number → Between 1 and 100
A23: 4 | B23: Discount_% (R) | C23: Decimal | D23: Min: 0 | Max: 80 | E23: Discount cannot exceed 80% | F23: Data → Validation → Decimal → Between 0 and 80
A24: 5 | B24: Unit_Price (Q) | C24: Decimal | D24: Min: 1 | Max: 500000 | E24: Price must be positive | F24: Data → Validation → Decimal → Greater than 0
A25: 6 | B25: Order_Date (B) | C25: Date | D25: End: =TODAY() | E25: Order date cannot be future | F25: Data → Validation → Date → Less than or equal to =TODAY()
A26: 7 | B26: Email (E) | C26: Custom Formula | D26: =AND(ISNUMBER(FIND("@",E3)),ISNUMBER(FIND(".",E3))) -> FALSE | E26: Invalid email format! Need @ and . | F26: Data → Validation → Custom → enter formula
A27: 8 | B27: Phone (F) | C27: Custom Formula | D27: =AND(LEN(F3)=10,ISNUMBER(VALUE(F3))) -> FALSE | E27: Phone must be exactly 10 digits | F27: Data → Validation → Custom → =AND(LEN(F3)=10,ISNUMBER(VALUE(F3)))
A28: 9 | B28: Return_Flag (V) | C28: List | D28: Source: Yes,No | E28: Select Yes or No only | F28: Data → Validation → List → Yes,No
A29: 10 | B29: Order_Status (U) | C29: List | D29: Source: =OrderStatusList | E29: Select valid status only | F29: Create named range, then apply list validation
A31: ✏️ PRACTICE SHEET — Enter data below. Validations are applied. Try entering invalid values!
A32: Order_ID | B32: Order_Date | C32: Customer_Name | D32: Region | E32: Category | F32: Quantity | G32: Unit_Price | H32: Discount_% | I32: Payment_Mode | J32: Order_Status
A33: ORD-XXXX | B33: 2024-06-15 | C33: Your Name Here | D33: South | E33: Electronics | F33: 2 | G33: 15000 | H33: 10 | I33: UPI | J33: Delivered
A34: ORD-YYYY | B34: 2024-07-20 | C34: Test User | D34: North | E34: Fashion | F34: 1 | G34: 3500 | H34: 15 | I34: Credit Card | J34: Shipped

Sheet Lists
A1: 📋 REFERENCE LISTS — Named Ranges for Data Validation Dropdowns
A2: Region | B2: Category | C2: Payment_Mode | D2: Order_Status | E2: Return_Flag | F2: Gender | G2: Sub_Category | H2: Brand
A3: North | B3: Electronics | C3: UPI | D3: Delivered | E3: Yes | F3: Male | G3: Mobile | H3: Samsung
A4: South | B4: Fashion | C4: Credit Card | D4: Shipped | E4: No | F4: Female | G4: Television | H4: Apple
A5: East | B5: Grocery | C5: Debit Card | D5: Returned | F5: Other | G5: Laptop | H5: Nike
A6: West | B6: Home | C6: Cash | D6: Cancelled | G6: Audio | H6: Prestige
B7: Jewellery | C7: EMI | D7: Pending | G7: Computer | H7: Boat
C8: Net Banking | G8: Footwear | H8: LG
G9: Clothing | H9: Levi's
G10: Accessories | H10: Nestlé
G11: Traditional | H11: HP
G12: Kitchen | H12: Fab India
G13: Appliance | H13: Whirlpool
G14: Beverage | H14: Britannia
G15: Snacks | H15: Titan
G16: Dairy | H16: Philips
G17: Lighting | H17: OnePlus
G18: Travel | H18: Adidas
G19: Gold | H19: Parle
H20: Voltas
H21: Fastrack
H22: Amul
H23: Realme
A25: 💡 To create named range: Select the list → click Name Box (left of formula bar) → type name (e.g., RegionList) → Enter. Then use =RegionList in Data Validation.

Sheet Chart_Data
A1: 📊 CHART DATA — Summarized Tables for Visualization
A2: TABLE 1: Sales by Region
A3: Region | B3: Total Sales (₹) | C3: Orders | D3: Avg Order (₹)
A4: North | B4: 1250000 | C4: 127 | D4: 9843
A5: South | B5: 1840000 | C5: 185 | D5: 9946
A6: East | B6: 860000 | C6: 86 | D6: 10000
A7: West | B7: 1520000 | C7: 152 | D7: 10000
A9: TABLE 2: Monthly Sales Trend
A10: Month | B10: Total Sales (₹) | C10: Orders | D10: Growth %
A11: Jan-2024 | B11: 420000 | C11: 42
A12: Feb-2024 | B12: 380000 | C12: 38 | D12: -9.5
A13: Mar-2024 | B13: 510000 | C13: 51 | D13: 34.2
A14: Apr-2024 | B14: 470000 | C14: 47 | D14: -7.8
A15: May-2024 | B15: 620000 | C15: 62 | D15: 31.9
A16: Jun-2024 | B16: 590000 | C16: 59 | D16: -4.8
A17: Jul-2024 | B17: 700000 | C17: 70 | D17: 18.6
A18: Aug-2024 | B18: 650000 | C18: 65 | D18: -7.1
A19: Sep-2024 | B19: 720000 | C19: 72 | D19: 10.8
A20: Oct-2024 | B20: 810000 | C20: 81 | D20: 12.5
A21: Nov-2024 | B21: 880000 | C21: 88 | D21: 8.6
A22: Dec-2024 | B22: 730000 | C22: 73 | D22: -17
A24: TABLE 3: Sales by Category
A25: Category | B25: Sales (₹) | C25: % Share | D25: Orders
A26: Electronics | B26: 2750000 | C26: 0.503 | D26: 275
A27: Fashion | B27: 1100000 | C27: 0.201 | D27: 165
A28: Home | B28: 820000 | C28: 0.15 | D28: 82
A29: Grocery | B29: 480000 | C29: 0.088 | D29: 120
A30: Jewellery | B30: 320000 | C30: 0.058 | D30: 32
A32: TABLE 4: Order Status Distribution
A33: Status | B33: Count | C33: % Share
A34: Delivered | B34: 365 | C34: 0.76
A35: Shipped | B35: 72 | C35: 0.15
A36: Returned | B36: 29 | C36: 0.06
A37: Cancelled | B37: 14 | C37: 0.03
A39: TABLE 5: Top 10 Products by Sales
A40: Product | B40: Sales (₹) | C40: Qty Sold | D40: Category
A41: iPhone 14 Pro | B41: 890000 | C41: 10 | D41: Electronics
A42: HP Pavilion Laptop | B42: 550000 | C42: 10 | D42: Electronics
A43: Whirlpool 1.5T AC | B43: 380000 | C43: 10 | D43: Home
A44: LG Refrigerator | B44: 420000 | C44: 10 | D44: Home
A45: Samsung TV 43" | B45: 350000 | C45: 10 | D45: Electronics
A46: OnePlus Nord CE 3 | B46: 280000 | C46: 10 | D46: Electronics
A47: Titan Raga Watch | B47: 255000 | C47: 30 | D47: Fashion
A48: Banarasi Silk Saree | B48: 245000 | C48: 70 | D48: Fashion
A49: Nike Running Shoes | B49: 225000 | C49: 50 | D49: Fashion
A50: Samsung Galaxy M14 | B50: 210000 | C50: 15 | D50: Electronics

Sheet Visualization_Guide
A1: 📊 DATA VISUALIZATION GUIDE — Charts, When to Use & How to Build
A3: CHART SELECTION GUIDE
A4: Chart Type | B4: Best Used For | C4: Example Use Case | D4: Data Needed | E4: Avoid When
A5: Column Chart | B5: Compare values across categories | C5: Sales by Region (North vs South vs East vs West) | D5: Category | Value | E5: Too many categories (>10)
A6: Bar Chart (Horizontal) | B6: Ranking or long category names | C6: Top 10 Products by Sales | D6: Item Name | Value | E6: Showing time trends
A7: Line Chart | B7: Show trend over time | C7: Monthly Sales Trend Jan–Dec | D7: Time Period | Value | E7: Comparing unrelated categories
A8: Pie Chart | B8: Show proportion of a whole | C8: Category-wise Sales Share | D8: Category | % | E8: More than 6 slices — use Donut
A9: Donut Chart | B9: Same as pie but with center info | C9: Order Status Distribution | D9: Status | Count | E9: Too many small slices
A10: Clustered Column | B10: Compare multiple series | C10: Sales vs Target by Region | D10: Category | Series1 | Series2 | E10: Too many series (>3)
A11: Area Chart | B11: Cumulative trend | C11: Running Total of Sales | D11: Time | Cumulative Value | E11: Non-time series data
A12: Scatter Plot | B12: Correlation between 2 variables | C12: Price vs Quantity Sold | D12: X value | Y value | E12: Categorical data
A14: HOW TO BUILD EACH CHART — Step-by-Step
A15: CHART 1: Sales by Region (Column Chart)
A16: 1. Go to Chart_Data sheet → Select A4:B8 (Region + Total Sales)
A17: 2. Insert tab → Charts group → Insert Column Chart → Clustered Column
A18: 3. Click Chart Title → Type 'Total Sales by Region'
A19: 4. Right-click bars → Add Data Labels → Show Values
A20: 5. Chart Design tab → Change Colors → choose blue family
A21: 6. Format: Remove gridlines, add axis titles (Region / Sales in ₹)
A23: CHART 2: Monthly Sales Trend (Line Chart)
A24: 1. Select Chart_Data!A13:B25 (Month + Sales)
A25: 2. Insert → Charts → Line → Line with Markers
A26: 3. Right-click line → Add Trendline → Linear → check 'Display Equation'
... A48: ❌ COMMON CHART MISTAKES BEGINNERS MAKE
A49: ❌ MISTAKE | F49: ✅ CORRECT APPROACH
A50: Using 3D charts (3D Pie, 3D Column) | F50: Use 2D charts only — 3D distorts visual perception
A51: Pie chart with 7+ slices | F51: Group small slices into 'Other' — max 6 slices
A52: No chart title or axis labels | F52: Always add: Title + X-axis + Y-axis labels + Units
A53: Too many colors (rainbow charts) | F53: Use 1–3 colors max. Use color to highlight important data only
A54: Line chart for categories (non-time) | F54: Line = time series only. Use Bar/Column for categories
A55: Starting Y-axis at non-zero to exaggerate | F55: Keep Y-axis at 0 unless justified. Misleads viewers
A56: No data labels on pie chart | F56: Always show % labels on pie/donut charts
A57: Cluttered chart with too much data | F57: Simplify — one chart = one message

Sheet Dashboard
A1: 🛒 E-COMMERCE SALES PERFORMANCE DASHBOARD — FY 2024 | India Region
A2: Data Source: Flipkart-style E-Commerce Dataset | 480 Clean Records | January – June 2024 | Last Updated: April 2025
A4: 💰 Total Sales | D4: 📦 Total Orders | G4: 📈 Avg Order Value | J4: ✅ Delivered % | M4: 🔄 Return Rate
A5: ₹54,70,000 | D5: 480 | G5: ₹11,396 | J5: 76.0% | M5: 6.0%
A6: +12.3% vs LY | D6: ↑ 8.2% MoM | G6: Target: ₹10,000 | J6: Target: 80% | M6: Below 7% = Good
A9: 📊 SALES BY REGION | H9: 📈 MONTHLY SALES TREND
A10: Region | B10: Sales (₹) | C10: Orders | D10: Avg Order | E10: % Share | F10: Status | H10: Month | I10: Sales | J10: Orders | K10: Growth | L10: Target Hit?
A11: North | B11: ₹12,50,000 | C11: 127 | D11: ₹9,843 | E11: 22.8% | F11: ⬆ Good | H11: Jan | I11: ₹4,20,000 | J11: 42 | K11: - | L11: ✅
A12: South | B12: ₹18,40,000 | C12: 185 | D12: ₹9,946 | E12: 33.6% | F12: ⬆ Best | H12: Feb | I12: ₹3,80,000 | J12: 38 | K12: -9.5% | L12: ❌
A13: East | B13: ₹8,60,000 | C13: 86 | D13: ₹10,000 | E13: 15.7% | F13: → Average | H13: Mar | I13: ₹5,10,000 | J13: 51 | K13: +34.2% | L13: ✅
A14: West | B14: ₹15,20,000 | C14: 152 | D14: ₹10,000 | E14: 27.8% | F14: ⬆ Good | H14: Apr | I14: ₹4,70,000 | J14: 47 | K14: -7.8% | L14: ✅
H15: May | I15: ₹6,20,000 | J15: 62 | K15: +31.9% | L15: ✅
H16: Jun | I16: ₹5,90,000 | J16: 59 | K16: -4.8% | L16: ✅
A17: 🥧 CATEGORY PERFORMANCE | H17: 🏆 TOP 5 PRODUCTS
A18: Category | B18: Sales (₹) | C18: Share | D18: Orders | E18: Avg (₹) | F18: Rank | H18: Product | I18: Category | J18: Sales | K18: Orders | L18: Rank
A19: Electronics | B19: ₹27,50,000 | C19: 50.3% | D19: 275 | E19: ₹10,000 | F19: 1 | H19: iPhone 14 Pro | I19: Electronics | J19: ₹8,90,000 | K19: 10 | L19: 1
A20: Fashion | B20: ₹11,00,000 | C20: 20.1% | D20: 165 | E20: ₹6,667 | F20: 2 | H20: HP Laptop | I20: Electronics | J20: ₹5,50,000 | K20: 10 | L20: 2
A21: Home | B21: ₹8,20,000 | C21: 15.0% | D21: 82 | E21: ₹10,000 | F21: 3 | H21: LG Refrigerator | I21: Home | J21: ₹4,20,000 | K21: 10 | L21: 3
A22: Grocery | B22: ₹4,80,000 | C22: 8.8% | D22: 120 | E22: ₹4,000 | F22: 4 | H22: Whirlpool AC | I22: Home | J22: ₹3,80,000 | K22: 10 | L22: 4
A23: Jewellery | B23: ₹3,20,000 | C23: 5.8% | D23: 32 | E23: ₹10,000 | F23: 5 | H23: Samsung TV | I23: Electronics | J23: ₹3,50,000 | K23: 10 | L23: 5
A25: 📌 NEXT STEPS: 1) Create Pivot Tables from Clean_Data sheet 2) Insert PivotCharts 3) Add Slicers for Region, Category, Order_Status 4) Add Timeline for Order_Date 5) Connect all slicers via Report Connections

Sheet Assignment
A1: 🎯 MINI PROJECT ASSIGNMENT — Student Performance Data Cleaning & Dashboard
A2: Telugu: Ee assignment complete chesi screenshot comment lo share cheyyandi. Best submissions featured avutaayi!
A3: TASKS (Total: 100 Marks)
A4: # | B4: Task | C4: Details | D4: Marks | E4: Your Answer
A5: 1 | B5: TRIM + PROPER on Student Names | C5: Remove spaces, fix casing | D5: 10
A6: 2 | B6: Remove Duplicate Student_IDs | C6: Use COUNTIF + Remove Duplicates | D6: 10
A7: 3 | B7: Handle Blank Names | C7: Fill with 'Unknown Student' | D7: 10
A8: 4 | B8: Fix Invalid CGPA (>10 or <0) | C8: Flag as 'Check Required' | D8: 10
A9: 5 | B9: Standardize Gender (M→Male, F→Female) | C9: Use IF/SWITCH formula | D9: 10
A10: 6 | B10: Data Validation on Placement_Status | C10: Dropdown: Placed/Not Placed | D10: 10
A11: 7 | B11: Chart: Avg CGPA by Branch | C11: Clustered Column Chart | D11: 15
A12: 8 | B12: Chart: Placement Rate by College | C12: Pie/Donut Chart | D12: 15
A13: 9 | B13: Build a Mini KPI Dashboard | C13: 3 KPI cards + 2 charts | D13: 10
A14: TOTAL: 100 Marks | Submission: Screenshot in YouTube comments | Deadline: 7 days from video upload
A16: ASSIGNMENT DATASET — Student Performance Data (With Issues)
A17: Student_ID | B17: Name | C17: College | D17: City | E17: Branch | F17: Semester | G17: CGPA | H17: Attendance_% | I17: Backlogs | J17: Placement_Status | K17: Package_LPA | L17: Gender | M17: Year_of_Passing
A18: STU-1001 | B18: anita verma | C18: Andhra University | D18: Kolkata | E18: EEE | F18: 3 | G18: 8.31 | H18: 99 | I18: 2 | J18: Placed | K18: 8.9 | L18: female | M18: 2024
A19: STU-1002 | B19: SNEHA REDDY | C19: IIT Hyderabad | D19: Bengaluru | E19: EEE | F19: 4 | G19: 8.48 | H19: 68 | I19: 5 | J19: Not Placed | K19: 13.6 | L19: Female | M19: 2023
A20: STU-1003 | B20: meera n | C20: BITS Pilani | D20: Kolkata | E20: Chemical | F20: 1 | G20: 5.33 | H20: 98.7 | I20: 2 | J20: placed | K20: 14.1 | L20: F | M20: 2024
A21: STU-1004 | B21: kabir mehta | C21: Osmania | D21: Bengaluru | E21: IT | F21: 7 | G21: 5.14 | H21: 85.8 | I21: 4 | J21: Not Placed | K21: 4.7 | L21: female | M21: 2023
A22: STU-1005 | B22: priya devi | C22: VIT | D22: Delhi | E22: EEE | F22: 1 | G22: 10.15 | H22: 75.1 | I22: 0 | J22: Placed | L22: FEMALE | M22: 2025
A23: STU-1005 | B23: Divya Nair | C23: IIT Hyderabad | D23: Bengaluru | E23: ECE | F23: 6 | G23: 5.78 | H23: 95.7 | I23: 4 | J23: Placed | L23: MALE | M23: 2023
A24: STU-1007 | B24: kavya rao | C24: JNTU | D24: Delhi | E24: ECE | F24: 2 | G24: 9.16 | H24: 52.2 | I24: 4 | J24: Not Placed | K24: 18.9 | L24: F | M24: 2023
A25: STU-1008 | B25: Divya Nair | C25: VIT | D25: Bengaluru | E25: IT | F25: 7 | G25: 10.35 | H25: 68.6 | I25: 5 | J25: Not Placed | K25: 19.5 | L25: Other | M25: 2023
A26: STU-1009 | B26: SNEHA REDDY | C26: VIT | D26: Hyderabad | E26: CSE | F26: 4 | G26: 7.47 | H26: 56.3 | I26: 3 | J26: Placed | K26: 8.7 | L26: Male | M26: 2024
A27: STU-1010 | B27: SNEHA REDDY | C27: BITS Pilani | D27: Pune | E27: Mechanical | F27: 1 | G27: 10.22 | H27: 102.5 | I27: 4 | J27: placed | L27: female | M27: 2023
A28: STU-1011 | C28: Osmania | D28: Chennai | E28: Mechanical | F28: 1 | G28: 8.93 | H28: 72.8 | I28: 2 | J28: not placed | L28: Female | M28: 2023
A29: STU-1012 | B29: AMIT SHAH | C29: BITS Pilani | D29: Chennai | E29: EEE | F29: 5 | G29: 9.94 | H29: 59 | I29: 4 | J29: placed | L29: Other | M29: 2025
A30: STU-1013 | B30: Arjun Singh | C30: NIT Warangal | D30: Hyderabad | E30: IT | F30: 5 | G30: 9.59 | H30: 91.5 | I30: 3 | J30: Placed | L30: female | M30: 2025
A31: STU-1014 | B31: SNEHA REDDY | C31: VIT | D31: Pune | E31: IT | F31: 5 | G31: 6.02 | H31: 52.3 | I31: 5 | J31: not placed | K31: 19.3 | L31: F | M31: 2023
A32: STU-1015 | B32: Divya Nair | C32: Osmania | D32: Chennai | E32: CSE | F32: 5 | G32: 7.55 | H32: 85.6 | I32: 0 | J32: Not Placed | L32: M | M32: 2023
A33: STU-1016 | B33: SNEHA REDDY | C33: NIT Warangal | D33: Bengaluru | E33: Civil | F33: 5 | G33: 7.75 | H33: 89.6 | I33: 5 | J33: Not Placed | K33: 13.1 | L33: Female | M33: 2023
A34: STU-1017 | B34: RAVI KUMAR | C34: NIT Warangal | D34: Pune | E34: Civil | F34: 3 | G34: 9.69 | H34: 84.1 | I34: 0 | J34: Placed | K34: 23.8 | L34: FEMALE | M34: 2024
A35: STU-1018 | C35: Andhra University | D35: Hyderabad | E35: CSE | F35: 5 | G35: 6.05 | H35: 73.3 | I35: 1 | J35: placed | K35: 4.7 | L35: female | M35: 2024
A36: STU-1019 | B36: priya devi | C36: JNTU | D36: Hyderabad | E36: CSE | F36: 4 | G36: 10.06 | H36: 90.9 | I36: 3 | J36: PLACED | K36: 3.7 | L36: Other | M36: 2023
A37: STU-1020 | B37: kabir mehta | C37: NIT Warangal | D37: Pune | E37: Mechanical | F37: 1 | G37: 5.12 | H37: 81 | I37: 0 | J37: NOT PLACED | L37: male | M37: 2025
A38: STU-1021 | B38: ROHIT YADAV | C38: BITS Pilani | D38: Mumbai | E38: IT | F38: 8 | G38: 5.96 | H38: 50.7 | I38: 1 | J38: placed | K38: 17.4 | L38: Male | M38: 2023
A39: STU-1022 | B39: SNEHA REDDY | C39: Andhra University | D39: Kolkata | E39: Mechanical | F39: 8 | G39: 6.29 | H39: 74.6 | I39: 1 | J39: not placed | L39: Male | M39: 2023
A40: STU-1023 | B40: Divya Nair | C40: BITS Pilani | D40: Chennai | E40: Civil | F40: 3 | G40: 5.49 | H40: 70.2 | I40: 2 | J40: not placed | K40: 15 | L40: FEMALE | M40: 2025
A41: STU-1024 | B41: Arjun Singh | C41: NIT Warangal | D41: Pune | E41: Civil | F41: 7 | G41: 8.19 | H41: 70.5 | I41: 2 | J41: NOT PLACED | K41: 19.9 | L41: Female | M41: 2023
A42: STU-1025 | B42: Arjun Singh | C42: JNTU | D42: Mumbai | E42: Civil | F42: 3 | G42: 6.83 | H42: 69.7 | I42: 4 | J42: placed | K42: 19.6 | L42: Other | M42: 2024
A43: STU-1026 | B43: kavya rao | C43: NIT Warangal | D43: Hyderabad | E43: Civil | F43: 1 | G43: 5.77 | H43: 94.9 | I43: 4 | J43: Placed | L43: Male | M43: 2023
A44: STU-1027 | B44: AMIT SHAH | C44: JNTU | D44: Mumbai | E44: IT | F44: 6 | G44: 8.66 | H44: 59.1 | I44: 4 | J44: NOT PLACED | L44: Other | M44: 2025
A45: STU-1028 | B45: SNEHA REDDY | C45: Osmania | D45: Kolkata | E45: IT | F45: 4 | G45: 8.17 | H45: 91.2 | I45: 5 | J45: Placed | K45: 24.7 | L45: Other | M45: 2023
A46: STU-1029 | B46: anita verma | C46: VIT | D46: Pune | E46: CSE | F46: 4 | G46: 5.79 | H46: 54 | I46: 0 | J46: Placed | K46: 8.3 | L46: Male | M46: 2023
A47: STU-1030 | B47: priya devi | C47: IIT Hyderabad | D47: Pune | E47: Mechanical | F47: 1 | G47: 6.14 | H47: 95.5 | I47: 5 | J47: PLACED | K47: 4.5 | L47: MALE | M47: 2023
A48: STU-1031 | B48: ROHIT YADAV | C48: BITS Pilani | D48: Bengaluru | E48: CSE | F48: 8 | G48: 7.06 | H48: 66.7 | I48: 2 | J48: placed | K48: 23.2 | L48: Male | M48: 2023
A49: STU-1032 | B49: meera n | C49: IIT Hyderabad | D49: Pune | E49: Mechanical | F49: 1 | G49: 7.6 | H49: 93.9 | I49: 3 | J49: Placed | K49: 19.9 | L49: female | M49: 2023
A50: STU-1033 | B50: anita verma | C50: JNTU | D50: Bengaluru | E50: Mechanical | F50: 6 | G50: 6.39 | H50: 55.1 | I50: 1 | J50: PLACED | L50: female | M50: 2023
A51: STU-1034 | C51: Osmania | D51: Chennai | E51: Chemical | F51: 1 | G51: 6.7 | H51: 92.7 | I51: 4 | J51: NOT PLACED | K51: 7.8 | L51: Female | M51: 2024
A52: STU-1035 | B52: anita verma | C52: JNTU | D52: Pune | E52: Civil | F52: 8 | G52: 6.51 | H52: 81.1 | I52: 1 | J52: NOT PLACED | K52: 14.8 | L52: MALE | M52: 2024
A53: STU-1036 | B53: RAVI KUMAR | C53: Osmania | D53: Bengaluru | E53: Mechanical | F53: 4 | G53: 6.6 | H53: 68.2 | I53: 0 | J53: NOT PLACED | L53: M | M53: 2025
A54: STU-1037 | B54: RAVI KUMAR | C54: Andhra University | D54: Pune | E54: CSE | F54: 2 | G54: 6.66 | H54: 62.3 | I54: 1 | J54: Not Placed | K54: 15.8 | L54: M | M54: 2023
A55: STU-1038 | B55: anita verma | C55: VIT | D55: Hyderabad | E55: Mechanical | F55: 8 | G55: 7.73 | H55: 93.7 | I55: 0 | J55: placed | K55: 18.6 | L55: male | M55: 2025
A56: STU-1039 | B56: priya devi | C56: Osmania | D56: Hyderabad | E56: CSE | F56: 3 | G56: 5.36 | H56: 64.5 | I56: 0 | J56: PLACED | K56: 10.9 | L56: M | M56: 2024
A57: STU-1040 | B57: anita verma | C57: VIT | D57: Bengaluru | E57: CSE | F57: 1 | G57: 8.63 | H57: 80 | I57: 1 | J57: Not Placed | K57: 13.5 | L57: M | M57: 2023
A58: STU-1041 | C58: VIT | D58: Pune | E58: EEE | F58: 1 | G58: 9.11 | H58: 71.5 | I58: 2 | J58: Not Placed | L58: FEMALE | M58: 2024
A59: STU-1042 | B59: anita verma | C59: BITS Pilani | D59: Pune | E59: Civil | F59: 2 | G59: 9.41 | H59: 60.4 | I59: 1 | J59: not placed | K59: 13.5 | L59: M | M59: 2024
A60: STU-1043 | B60: priya devi | C60: NIT Warangal | D60: Kolkata | E60: IT | F60: 6 | G60: 7.63 | H60: 104.4 | I60: 1 | J60: placed | L60: male | M60: 2023
A61: STU-1044 | B61: ROHIT YADAV | C61: IIT Hyderabad | D61: Bengaluru | E61: Mechanical | F61: 4 | G61: 5.24 | H61: 67.6 | I61: 5 | J61: Not Placed | L61: female | M61: 2025
A62: STU-1045 | B62: SURESH K | C62: JNTU | D62: Bengaluru | E62: Civil | F62: 1 | G62: 9.8 | H62: 84.9 | I62: 3 | J62: Placed | L62: Other | M62: 2023
A63: STU-1046 | B63: meera n | C63: Andhra University | D63: Mumbai | E63: EEE | F63: 6 | G63: 9.9 | H63: 58 | I63: 2 | J63: NOT PLACED | K63: 11.1 | L63: Other | M63: 2025
A64: STU-1047 | B64: ROHIT YADAV | C64: Andhra University | D64: Chennai | E64: ECE | F64: 8 | G64: 9.17 | H64: 96.2 | I64: 2 | J64: Placed | K64: 15.3 | L64: female | M64: 2023
A65: STU-1048 | B65: AMIT SHAH | C65: IIT Hyderabad | D65: Chennai | E65: Civil | F65: 4 | G65: 7.84 | H65: 84.7 | I65: 2 | J65: placed | L65: F | M65: 2024
A66: STU-1049 | B66: Divya Nair | C66: VIT | D66: Bengaluru | E66: IT | F66: 4 | G66: 10.35 | H66: 60.6 | I66: 4 | J66: Not Placed | L66: MALE | M66: 2024
A67: STU-1050 | B67: SURESH K | C67: JNTU | D67: Pune | E67: IT | F67: 5 | G67: 8.77 | H67: 89.2 | I67: 5 | J67: Not Placed | K67: 7.5 | L67: F | M67: 2023
A68: STU-1051 | B68: Arjun Singh | C68: VIT | D68: Bengaluru | E68: Civil | F68: 6 | G68: 9.88 | H68: 94.5 | I68: 1 | J68: placed | L68: Female | M68: 2023
A69: STU-1052 | B69: priya devi | C69: NIT Warangal | D69: Bengaluru | E69: Civil | F69: 5 | G69: 10.32 | H69: 94.7 | I69: 4 | J69: PLACED | K69: 3.1 | L69: male | M69: 2024
A70: STU-1053 | B70: kabir mehta | C70: JNTU | D70: Delhi | E70: ECE | F70: 2 | G70: 5.28 | H70: 73.5 | I70: 2 | J70: Placed | K70: 16.1 | L70: Male | M70: 2023
A71: STU-1054 | B71: kabir mehta | C71: NIT Warangal | D71: Delhi | E71: CSE | F71: 1 | G71: 5.59 | H71: 79.4 | I71: 0 | J71: Placed | L71: FEMALE | M71: 2023
A72: STU-1055 | B72: kabir mehta | C72: Andhra University | D72: Delhi | E72: ECE | F72: 1 | G72: 7.36 | H72: 62.7 | I72: 4 | J72: PLACED | K72: 15.6 | L72: FEMALE | M72: 2024
A73: STU-1056 | B73: Arjun Singh | C73: JNTU | D73: Chennai | E73: IT | F73: 5 | G73: 9.43 | H73: 95.4 | I73: 3 | J73: Placed | L73: Female | M73: 2024
A74: STU-1057 | B74: ROHIT YADAV | C74: JNTU | D74: Hyderabad | E74: ECE | F74: 5 | G74: 6.22 | H74: 75.3 | I74: 3 | J74: PLACED | L74: male | M74: 2025
A75: STU-1058 | B75: SNEHA REDDY | C75: Andhra University | D75: Chennai | E75: Chemical | F75: 7 | G75: 6.28 | H75: 96.6 | I75: 0 | J75: PLACED | K75: 12.8 | L75: MALE | M75: 2024
A76: STU-1059 | B76: SURESH K | C76: Andhra University | D76: Bengaluru | E76: Civil | F76: 4 | G76: 7.7 | H76: 93.4 | I76: 2 | J76: Not Placed | K76: 10.1 | L76: Female | M76: 2025
A77: STU-1060 | B77: Arjun Singh | C77: IIT Hyderabad | D77: Delhi | E77: Mechanical | F77: 8 | G77: 9.33 | H77: 61.4 | I77: 0 | J77: not placed | L77: F | M77: 2023
A78: STU-1060 | B78: anita verma | C78: NIT Warangal | D78: Bengaluru | E78: CSE | F78: 7 | G78: 8.92 | H78: 51.2 | I78: 2 | J78: placed | K78: 10.9 | L78: F | M78: 2023
A79: STU-1062 | B79: Divya Nair | C79: VIT | D79: Chennai | E79: Civil | F79: 4 | G79: 10.01 | H79: 64.3 | I79: 0 | J79: NOT PLACED | L79: FEMALE | M79: 2023
A80: STU-1063 | C80: JNTU | D80: Chennai | E80: EEE | F80: 8 | G80: 5.49 | H80: 100.4 | I80: 1 | J80: placed | L80: M | M80: 2025
A81: STU-1064 | B81: kabir mehta | C81: VIT | D81: Hyderabad | E81: Civil | F81: 3 | G81: 9.79 | H81: 60.2 | I81: 2 | J81: PLACED | K81: 6.7 | L81: female | M81: 2025
A82: STU-1065 | C82: JNTU | D82: Mumbai | E82: Chemical | F82: 3 | G82: 6.3 | H82: 94.4 | I82: 4 | J82: Placed | L82: female | M82: 2023
A83: STU-1066 | B83: meera n | C83: Osmania | D83: Kolkata | E83: EEE | F83: 1 | G83: 5.98 | H83: 79.4 | I83: 4 | J83: PLACED | L83: Male | M83: 2025
A84: STU-1067 | B84: Arjun Singh | C84: Andhra University | D84: Mumbai | E84: Mechanical | F84: 4 | G84: 5.92 | H84: 75.8 | I84: 3 | J84: Not Placed | K84: 8.3 | L84: Female | M84: 2024
A85: STU-1068 | C85: NIT Warangal | D85: Chennai | E85: Chemical | F85: 8 | G85: 8.52 | H85: 91.5 | I85: 5 | J85: NOT PLACED | L85: Other | M85: 2025
A86: STU-1069 | B86: AMIT SHAH | C86: NIT Warangal | D86: Kolkata | E86: EEE | F86: 7 | G86: 7.57 | H86: 85.6 | I86: 1 | J86: PLACED | K86: 20.3 | L86: female | M86: 2024
A87: STU-1070 | B87: RAVI KUMAR | C87: NIT Warangal | D87: Bengaluru | E87: Mechanical | F87: 5 | G87: 6.14 | H87: 83 | I87: 2 | J87: Placed | L87: FEMALE | M87: 2025
A88: STU-1071 | B88: SNEHA REDDY | C88: Andhra University | D88: Pune | E88: ECE | F88: 5 | G88: 9.13 | H88: 61.9 | I88: 3 | J88: Not Placed | K88: 19.5 | L88: M | M88: 2023
A89: STU-1072 | B89: SNEHA REDDY | C89: Osmania | D89: Bengaluru | E89: ECE | F89: 7 | G89: 9.97 | H89: 63.9 | I89: 0 | J89: Not Placed | L89: M | M89: 2023
A90: STU-1073 | B90: kabir mehta | C90: IIT Hyderabad | D90: Mumbai | E90: Chemical | F90: 8 | G90: 7.06 | H90: 69.3 | I90: 0 | J90: NOT PLACED | K90: 22.5 | L90: Female | M90: 2023
A91: STU-1074 | B91: Divya Nair | C91: BITS Pilani | D91: Chennai | E91: EEE | F91: 1 | G91: 6.06 | H91: 100.7 | I91: 0 | J91: PLACED | L91: F | M91: 2023
A92: STU-1075 | B92: RAVI KUMAR | C92: Andhra University | D92: Chennai | E92: Civil | F92: 2 | G92: 7.47 | H92: 68.4 | I92: 3 | J92: NOT PLACED | K92: 10.6 | L92: male | M92: 2023
A93: STU-1076 | B93: SURESH K | C93: NIT Warangal | D93: Mumbai | E93: IT | F93: 8 | G93: 9.29 | H93: 90.1 | I93: 5 | J93: not placed | K93: 4.5 | L93: MALE | M93: 2024
A94: STU-1077 | C94: JNTU | D94: Delhi | E94: ECE | F94: 7 | G94: 9.19 | H94: 60.8 | I94: 4 | J94: Not Placed | K94: 9.1 | L94: male | M94: 2024
A95: STU-1078 | B95: ROHIT YADAV | C95: IIT Hyderabad | D95: Pune | E95: Mechanical | F95: 2 | G95: 8.01 | H95: 64 | I95: 1 | J95: NOT PLACED | K95: 3 | L95: M | M95: 2025
A96: STU-1079 | B96: priya devi | C96: IIT Hyderabad | D96: Chennai | E96: Civil | F96: 6 | G96: 5.44 | H96: 75.3 | I96: 5 | J96: not placed | K96: 16.6 | L96: FEMALE | M96: 2024
A97: STU-1080 | B97: SURESH K | C97: Osmania | D97: Kolkata | E97: CSE | F97: 7 | G97: 8.75 | H97: 89.4 | I97: 3 | J97: placed | K97: 9.1 | L97: FEMALE | M97: 2023
A98: STU-1081 | B98: anita verma | C98: IIT Hyderabad | D98: Hyderabad | E98: Chemical | F98: 3 | G98: 10.35 | H98: 104.5 | I98: 4 | J98: Not Placed | L98: F | M98: 2024
A99: STU-1082 | B99: anita verma | C99: VIT | D99: Mumbai | E99: EEE | F99: 2 | G99: 9.98 | H99: 100.9 | I99: 1 | J99: Not Placed | K99: 14.1 | L99: female | M99: 2023
A100: STU-1083 | B100: Divya Nair | C100: IIT Hyderabad | D100: Mumbai | E100: CSE | F100: 5 | G100: 10.09 | H100: 53.1 | I100: 1 | J100: NOT PLACED | K100: 12.5 | L100: female | M100: 2025
A101: STU-1084 | B101: kavya rao | C101: IIT Hyderabad | D101: Delhi | E101: Civil | F101: 6 | G101: 6.18 | H101: 73.7 | I101: 4 | J101: NOT PLACED | L101: Female | M101: 2023
...
